Workbook
Name Categoria: 'Validación'!$A$2:$A$10
Name Tipo: 'Validación'!$B$2:$B$4
Name Subcategoria: 'Validación'!$C$2:$C$28

Sheet Global Precios
A1: ID | B1: Codigo de barras | C1: Tipo | D1: Producto | E1: Marca | F1: Categoría | G1: Subcategoría | H1: Costo unitario s/iva | I1: Descuento | J1: Costo c/Iva | K1: Margen | L1: Precio al publico c/iva | M1: Presentación | N1: Unidad | O1: KG al publico | P1: Ultima Actualización | Q1: Longitud | R1: Frec. de actu | T1: Limpio de lista | U1: Dividir por: | V1: Costo c/iva a pasar: | W1: % de aumento | X1: Foto Producto | Y1: Stock | Z1: Uso | AA1: Codigo proveedor
A2: 1 | C2: Servicio | D2: Castración Gata | E2: Arlekyn | F2: Clinica | H2: =IF(J2="","",J2/1.21) -> 68163.636 | J2: 82478 | L2: =IF('Global Precios'!J2*(1-I2)*(1+'Global Precios'!K2)>10000,MROUND('Global Precios'!J2*(1-I2)*(1+'Global Precios'!K2),1000),MROUND('Global Precios'!J2*(1-I2)*(1+'Global Precios'!K2),500)) -> 82000 | M2: 1 | N2: c/u | P2: 45809 | Q2: =LEN(D2) -> 15 | R2: 60 | T2: =IFERROR(VLOOKUP(D2,BUSCARV!$A$1:$C$5524,2,0),"") | V2: =IF(U2="",T2,T2/U2) | W2: =IF(V2="","", IFERROR((V2-J2)/J2,"")) | Y2: =IFERROR(VLOOKUP(A2,#REF!,3,0),0) -> 0 | Z2: Activo
A3: 2 | C3: Servicio | D3: Castración perra hasta 10 kg | E3: Arlekyn | F3: Clinica | H3: =IF(J3="","",J3/1.21) -> 83251.24 | J3: 100734 | L3: =IF('Global Precios'!J3*(1-I3)*(1+'Global Precios'!K3)>10000,MROUND('Global Precios'!J3*(1-I3)*(1+'Global Precios'!K3),1000),MROUND('Global Precios'!J3*(1-I3)*(1+'Global Precios'!K3),500)) -> 101000 | M3: 1 | N3: c/u | P3: 45809 | Q3: =LEN(D3) -> 28 | R3: 60 | T3: =IFERROR(VLOOKUP(D3,BUSCARV!$A$1:$C$5524,2,0),"") | V3: =IF(U3="",T3,T3/U3) | W3: =IF(V3="","", IFERROR((V3-J3)/J3,"")) | Y3: =IFERROR(VLOOKUP(A3,#REF!,3,0),0) -> 0 | Z3: Activo
A4: 3 | C4: Servicio | D4: Castración perra hasta 20 kg | E4: Arlekyn | F4: Clinica | H4: =IF(J4="","",J4/1.21) -> 85819.835 | J4: 103842 | L4: =IF('Global Precios'!J4*(1-I4)*(1+'Global Precios'!K4)>10000,MROUND('Global Precios'!J4*(1-I4)*(1+'Global Precios'!K4),1000),MROUND('Global Precios'!J4*(1-I4)*(1+'Global Precios'!K4),500)) -> 104000 | M4: 1 | N4: c/u | P4: 45809 | Q4: =LEN(D4) -> 28 | R4: 60 | T4: =IFERROR(VLOOKUP(D4,BUSCARV!$A$1:$C$5524,2,0),"") | V4: =IF(U4="",T4,T4/U4) | W4: =IF(V4="","", IFERROR((V4-J4)/J4,"")) | Y4: =IFERROR(VLOOKUP(A4,#REF!,3,0),0) -> 0 | Z4: Activo
A5: 4 | C5: Servicio | D5: Castración perra hasta 30 kg | E5: Arlekyn | F5: Clinica | H5: =IF(J5="","",J5/1.21) -> 90454.545 | J5: 109450 | L5: =IF('Global Precios'!J5*(1-I5)*(1+'Global Precios'!K5)>10000,MROUND('Global Precios'!J5*(1-I5)*(1+'Global Precios'!K5),1000),MROUND('Global Precios'!J5*(1-I5)*(1+'Global Precios'!K5),500)) -> 109000 | M5: 1 | N5: c/u | P5: 45809 | Q5: =LEN(D5) -> 28 | R5: 60 | T5: =IFERROR(VLOOKUP(D5,BUSCARV!$A$1:$C$5524,2,0),"") | V5: =IF(U5="",T5,T5/U5) | W5: =IF(V5="","", IFERROR((V5-J5)/J5,"")) | Y5: =IFERROR(VLOOKUP(A5,#REF!,3,0),0) -> 0 | Z5: Activo
A6: 5 | C6: Servicio | D6: Castración perra hasta 40 kg | E6: Arlekyn | F6: Clinica | H6: =IF(J6="","",J6/1.21) -> 97890.083 | J6: 118447 | L6: =IF('Global Precios'!J6*(1-I6)*(1+'Global Precios'!K6)>10000,MROUND('Global Precios'!J6*(1-I6)*(1+'Global Precios'!K6),1000),MROUND('Global Precios'!J6*(1-I6)*(1+'Global Precios'!K6),500)) -> 118000 | M6: 1 | N6: c/u | P6: 45809 | Q6: =LEN(D6) -> 28 | R6: 60 | T6: =IFERROR(VLOOKUP(D6,BUSCARV!$A$1:$C$5524,2,0),"") | V6: =IF(U6="",T6,T6/U6) | W6: =IF(V6="","", IFERROR((V6-J6)/J6,"")) | Y6: =IFERROR(VLOOKUP(A6,#REF!,3,0),0) -> 0 | Z6: Activo
A7: 6 | C7: Servicio | D7: Castración perra hasta 50 kg | E7: Arlekyn | F7: Clinica | H7: =IF(J7="","",J7/1.21) -> 105325.62 | J7: 127444 | L7: =IF('Global Precios'!J7*(1-I7)*(1+'Global Precios'!K7)>10000,MROUND('Global Precios'!J7*(1-I7)*(1+'Global Precios'!K7),1000),MROUND('Global Precios'!J7*(1-I7)*(1+'Global Precios'!K7),500)) -> 127000 | M7: 1 | N7: c/u | P7: 45809 | Q7: =LEN(D7) -> 28 | R7: 60 | T7: =IFERROR(VLOOKUP(D7,BUSCARV!$A$1:$C$5524,2,0),"") | V7: =IF(U7="",T7,T7/U7) | W7: =IF(V7="","", IFERROR((V7-J7)/J7,"")) | Y7: =IFERROR(VLOOKUP(A7,#REF!,3,0),0) -> 0 | Z7: Activo
A8: 7 | C8: Servicio | D8: Castración perra hasta 60 kg | E8: Arlekyn | F8: Clinica | H8: =IF(J8="","",J8/1.21) -> 114000.83 | J8: 137941 | L8: =IF('Global Precios'!J8*(1-I8)*(1+'Global Precios'!K8)>10000,MROUND('Global Precios'!J8*(1-I8)*(1+'Global Precios'!K8),1000),MROUND('Global Precios'!J8*(1-I8)*(1+'Global Precios'!K8),500)) -> 138000 | M8: 1 | N8: c/u | P8: 45809 | Q8: =LEN(D8) -> 28 | R8: 60 | T8: =IFERROR(VLOOKUP(D8,BUSCARV!$A$1:$C$5524,2,0),"") | V8: =IF(U8="",T8,T8/U8) | W8: =IF(V8="","", IFERROR((V8-J8)/J8,"")) | Y8: =IFERROR(VLOOKUP(A8,#REF!,3,0),0) -> 0 | Z8: Activo
A9: 8 | C9: Servicio | D9: Corte de colitas camadas hasta 3 cachorros | E9: Arlekyn | F9: Clinica | H9: =IF(J9="","",J9/1.21) -> 14871.074 | J9: 17994 | L9: =IF('Global Precios'!J9*(1-I9)*(1+'Global Precios'!K9)>1000,MROUND('Global Precios'!J9*(1-I9)*(1+'Global Precios'!K9),100),MROUND('Global Precios'!J9*(1-I9)*(1+'Global Precios'!K9),10)) -> 18000 | M9: 1 | N9: c/u | P9: 45809 | Q9: =LEN(D9) -> 42 | R9: 60 | T9: =IFERROR(VLOOKUP(D9,BUSCARV!$A$1:$C$5524,2,0),"") | V9: =IF(U9="",T9,T9/U9) | W9: =IF(V9="","", IFERROR((V9-J9)/J9,"")) | Y9: =IFERROR(VLOOKUP(A9,#REF!,3,0),0) -> 0 | Z9: Desactivado
A10: 9 | C10: Servicio | D10: Corte de colitas camadas hasta 4 cachorros | E10: Arlekyn | F10: Clinica | H10: =IF(J10="","",J10/1.21) -> 12143.802 | J10: 14694 | L10: =IF('Global Precios'!J10*(1-I10)*(1+'Global Precios'!K10)>1000,MROUND('Global Precios'!J10*(1-I10)*(1+'Global Precios'!K10),100),MROUND('Global Precios'!J10*(1-I10)*(1+'Global Precios'!K10),10)) -> 14700 | M10: 1 | N10: c/u | P10: 45809 | Q10: =LEN(D10) -> 42 | R10: 60 | T10: =IFERROR(VLOOKUP(D10,BUSCARV!$A$1:$C$5524,2,0),"") | V10: =IF(U10="",T10,T10/U10) | W10: =IF(V10="","", IFERROR((V10-J10)/J10,"")) | Y10: =IFERROR(VLOOKUP(A10,#REF!,3,0),0) -> 0 | Z10: Desactivado
A11: 10 | C11: Servicio | D11: Eutanasia hasta 10 kg | E11: Arlekyn | F11: Clinica | H11: =IF(J11="","",J11/1.21) -> 50544.628 | J11: 61159 | L11: =IF('Global Precios'!J11*(1-I11)*(1+'Global Precios'!K11)>10000,MROUND('Global Precios'!J11*(1-I11)*(1+'Global Precios'!K11),1000),MROUND('Global Precios'!J11*(1-I11)*(1+'Global Precios'!K11),500)) -> 61000 | M11: 1 | N11: c/u | P11: 45809 | Q11: =LEN(D11) -> 21 | R11: 60 | T11: =IFERROR(VLOOKUP(D11,BUSCARV!$A$1:$C$5524,2,0),"") | V11: =IF(U11="",T11,T11/U11) | W11: =IF(V11="","", IFERROR((V11-J11)/J11,"")) | Y11: =IFERROR(VLOOKUP(A11,#REF!,3,0),0) -> 0 | Z11: Activo
A12: 11 | C12: Servicio | D12: Eutanasia hasta 20 kg | E12: Arlekyn | F12: Clinica | H12: =IF(J12="","",J12/1.21) -> 60022.314 | J12: 72627 | L12: =IF('Global Precios'!J12*(1-I12)*(1+'Global Precios'!K12)>10000,MROUND('Global Precios'!J12*(1-I12)*(1+'Global Precios'!K12),1000),MROUND('Global Precios'!J12*(1-I12)*(1+'Global Precios'!K12),500)) -> 73000 | M12: 1 | N12: c/u | P12: 45809 | Q12: =LEN(D12) -> 21 | R12: 60 | T12: =IFERROR(VLOOKUP(D12,BUSCARV!$A$1:$C$5524,2,0),"") | V12: =IF(U12="",T12,T12/U12) | W12: =IF(V12="","", IFERROR((V12-J12)/J12,"")) | Y12: =IFERROR(VLOOKUP(A12,#REF!,3,0),0) -> 0 | Z12: Activo
A13: 12 | C13: Servicio | D13: Eutanasia hasta 30 kg | E13: Arlekyn | F13: Clinica | H13: =IF(J13="","",J13/1.21) -> 71605.785 | J13: 86643 | L13: =IF('Global Precios'!J13*(1-I13)*(1+'Global Precios'!K13)>10000,MROUND('Global Precios'!J13*(1-I13)*(1+'Global Precios'!K13),1000),MROUND('Global Precios'!J13*(1-I13)*(1+'Global Precios'!K13),500)) -> 87000 | M13: 1 | N13: c/u | P13: 45809 | Q13: =LEN(D13) -> 21 | R13: 60 | T13: =IFERROR(VLOOKUP(D13,BUSCARV!$A$1:$C$5524,2,0),"") | V13: =IF(U13="",T13,T13/U13) | W13: =IF(V13="","", IFERROR((V13-J13)/J13,"")) | Y13: =IFERROR(VLOOKUP(A13,#REF!,3,0),0) -> 0 | Z13: Activo
A14: 13 | C14: Servicio | D14: Eutanasia hasta 40 kg | E14: Arlekyn | F14: Clinica | H14: =IF(J14="","",J14/1.21) -> 82136.364 | J14: 99385 | L14: =IF('Global Precios'!J14*(1-I14)*(1+'Global Precios'!K14)>10000,MROUND('Global Precios'!J14*(1-I14)*(1+'Global Precios'!K14),1000),MROUND('Global Precios'!J14*(1-I14)*(1+'Global Precios'!K14),500)) -> 99000 | M14: 1 | N14: c/u | P14: 45809 | Q14: =LEN(D14) -> 21 | R14: 60 | T14: =IFERROR(VLOOKUP(D14,BUSCARV!$A$1:$C$5524,2,0),"") | V14: =IF(U14="",T14,T14/U14) | W14: =IF(V14="","", IFERROR((V14-J14)/J14,"")) | Y14: =IFERROR(VLOOKUP(A14,#REF!,3,0),0) -> 0 | Z14: Activo
A15: 14 | C15: Servicio | D15: Eutanasia hasta 50 kg | E15: Arlekyn | F15: Clinica | H15: =IF(J15="","",J15/1.21) -> 90454.545 | J15: 109450 | L15: =IF('Global Precios'!J15*(1-I15)*(1+'Global Precios'!K15)>10000,MROUND('Global Precios'!J15*(1-I15)*(1+'Global Precios'!K15),1000),MROUND('Global Precios'!J15*(1-I15)*(1+'Global Precios'!K15),500)) -> 109000 | M15: 1 | N15: c/u | P15: 45809 | Q15: =LEN(D15) -> 21 | R15: 60 | T15: =IFERROR(VLOOKUP(D15,BUSCARV!$A$1:$C$5524,2,0),"") | V15: =IF(U15="",T15,T15/U15) | W15: =IF(V15="","", IFERROR((V15-J15)/J15,"")) | Y15: =IFERROR(VLOOKUP(A15,#REF!,3,0),0) -> 0 | Z15: Activo
A16: 15 | C16: Servicio | D16: consulta + Internación medio día PROMEDIO | E16: Arlekyn | F16: Clinica | H16: =IF(J16="","",J16/1.21) -> 29740.496 | J16: 35986 | L16: =IF('Global Precios'!J16*(1-I16)*(1+'Global Precios'!K16)>10000,MROUND('Global Precios'!J16*(1-I16)*(1+'Global Precios'!K16),1000),MROUND('Global Precios'!J16*(1-I16)*(1+'Global Precios'!K16),500)) -> 36000 | M16: 1 | N16: c/u | P16: 45809 | Q16: =LEN(D16) -> 41 | R16: 60 | T16: =IFERROR(VLOOKUP(D16,BUSCARV!$A$1:$C$5524,2,0),"") | V16: =IF(U16="",T16,T16/U16) | W16: =IF(V16="","", IFERROR((V16-J16)/J16,"")) | Y16: =IFERROR(VLOOKUP(A16,#REF!,3,0),0) -> 0 | Z16: Desactivado
A17: 16 | C17: Servicio | D17: Medio día sin consulta PROMEDIO | E17: Arlekyn | F17: Clinica | H17: =IF(J17="","",J17/1.21) -> 18587.603 | J17: 22491 | L17: =IF('Global Precios'!J17*(1-I17)*(1+'Global Precios'!K17)>10000,MROUND('Global Precios'!J17*(1-I17)*(1+'Global Precios'!K17),1000),MROUND('Global Precios'!J17*(1-I17)*(1+'Global Precios'!K17),500)) -> 22000 | M17: 1 | N17: c/u | P17: 45809 | Q17: =LEN(D17) -> 31 | R17: 60 | T17: =IFERROR(VLOOKUP(D17,BUSCARV!$A$1:$C$5524,2,0),"") | V17: =IF(U17="",T17,T17/U17) | W17: =IF(V17="","", IFERROR((V17-J17)/J17,"")) | Y17: =IFERROR(VLOOKUP(A17,#REF!,3,0),0) -> 0 | Z17: Activo
A18: 17 | C18: Servicio | D18: Consulta + día completo PROMEDIO | E18: Arlekyn | F18: Clinica | H18: =IF(J18="","",J18/1.21) -> 40890.083 | J18: 49477 | L18: =IF('Global Precios'!J18*(1-I18)*(1+'Global Precios'!K18)>10000,MROUND('Global Precios'!J18*(1-I18)*(1+'Global Precios'!K18),1000),MROUND('Global Precios'!J18*(1-I18)*(1+'Global Precios'!K18),500)) -> 49000 | M18: 1 | N18: c/u | P18: 45809 | Q18: =LEN(D18) -> 32 | R18: 60 | T18: =IFERROR(VLOOKUP(D18,BUSCARV!$A$1:$C$5524,2,0),"") | V18: =IF(U18="",T18,T18/U18) | W18: =IF(V18="","", IFERROR((V18-J18)/J18,"")) | Y18: =IFERROR(VLOOKUP(A18,#REF!,3,0),0) -> 0 | Z18: Activo
A19: 18 | C19: Servicio | D19: Día completo sin consulta PROMEDIO | E19: Arlekyn | F19: Clinica | H19: =IF(J19="","",J19/1.21) -> 32214.876 | J19: 38980 | L19: =IF('Global Precios'!J19*(1-I19)*(1+'Global Precios'!K19)>10000,MROUND('Global Precios'!J19*(1-I19)*(1+'Global Precios'!K19),1000),MROUND('Global Precios'!J19*(1-I19)*(1+'Global Precios'!K19),500)) -> 39000 | M19: 1 | N19: c/u | P19: 45809 | Q19: =LEN(D19) -> 34 | R19: 60 | T19: =IFERROR(VLOOKUP(D19,BUSCARV!$A$1:$C$5524,2,0),"") | V19: =IF(U19="",T19,T19/U19) | W19: =IF(V19="","", IFERROR((V19-J19)/J19,"")) | Y19: =IFERROR(VLOOKUP(A19,#REF!,3,0),0) -> 0 | Z19: Activo
A20: 19 | C20: Servicio | D20: Corte de uñas | E20: Arlekyn | F20: Clinica | H20: =IF(J20="","",J20/1.21) -> 5003.3058 | J20: 6054 | L20: =IF('Global Precios'!J20*(1-I20)*(1+'Global Precios'!K20)>10000,MROUND('Global Precios'!J20*(1-I20)*(1+'Global Precios'!K20),1000),MROUND('Global Precios'!J20*(1-I20)*(1+'Global Precios'!K20),500)) -> 6000 | M20: 1 | N20: c/u | P20: 45809 | Q20: =LEN(D20) -> 13 | R20: 60 | T20: =IFERROR(VLOOKUP(D20,BUSCARV!$A$1:$C$5524,2,0),"") | V20: =IF(U20="",T20,T20/U20) | W20: =IF(V20="","", IFERROR((V20-J20)/J20,"")) | Y20: =IFERROR(VLOOKUP(A20,#REF!,3,0),0) -> 0 | Z20: Activo
A21: 20 | C21: Servicio | D21: Consulta clinica | E21: Arlekyn | F21: Clinica | H21: =IF(J21="","",J21/1.21) -> 12143.802 | J21: 14694 | L21: =IF('Global Precios'!J21*(1-I21)*(1+'Global Precios'!K21)>10000,MROUND('Global Precios'!J21*(1-I21)*(1+'Global Precios'!K21),1000),MROUND('Global Precios'!J21*(1-I21)*(1+'Global Precios'!K21),500)) -> 15000 | M21: 1 | N21: c/u | P21: 45809 | Q21: =LEN(D21) -> 16 | R21: 60 | T21: =IFERROR(VLOOKUP(D21,BUSCARV!$A$1:$C$5524,2,0),"") | V21: =IF(U21="",T21,T21/U21) | W21: =IF(V21="","", IFERROR((V21-J21)/J21,"")) | Y21: =IFERROR(VLOOKUP(A21,#REF!,3,0),0) -> 0 | Z21: Activo
A22: 21 | B22: 12393470 | C22: Producto | D22: EXCELLENT PUPPY(r.medianas y grandes) Present:15kg | E22: Excellent | F22: Alimentos | G22: Perro | H22: =IF(J22="","",J22/1.21) -> 49917.355 | I22: 0.065 | J22: 60400 | K22: 0.33 | L22: =IF('Global Precios'!J22*(1-I22)*(1+'Global Precios'!K22)>10000,MROUND('Global Precios'!J22*(1-I22)*(1+'Global Precios'!K22),1000),MROUND('Global Precios'!J22*(1-I22)*(1+'Global Precios'!K22),500)) -> 75000 | M22: 15 | N22: kg | O22: =+MROUND(('Global Precios'!$J22/('Global Precios'!$M22))*(1+'Global Precios'!$K22+0.1),10) -> 5760 | P22: 46174 | Q22: =LEN(D22) -> 50 | R22: 30 | T22: =IFERROR(VLOOKUP(D22,BUSCARV!$A$1:$C$5524,2,0),"") | V22: =IF(U22="",T22,T22/U22) | W22: =IF(V22="","", IFERROR((V22-J22)/J22,"")) | Y22: =IFERROR(VLOOKUP(A22,#REF!,3,0),0) -> 0 | Z22: Desactivado
A23: 22 | B23: 12393468 | C23: Producto | D23: EXCELLENT ADULT.(r. medianas y grandes) Pres:15kg | E23: Excellent | F23: Alimentos | G23: Perro | H23: =IF(J23="","",J23/1.21) -> 17839.669 | I23: 0.065 | J23: 21586 | K23: 0.33 | L23: =IF('Global Precios'!J23*(1-I23)*(1+'Global Precios'!K23)>1000,MROUND('Global Precios'!J23*(1-I23)*(1+'Global Precios'!K23),100),MROUND('Global Precios'!J23*(1-I23)*(1+'Global Precios'!K23),10)) -> 26800 | M23: 15 | N23: kg | O23: =+MROUND(('Global Precios'!$J23/('Global Precios'!$M23))*(1+'Global Precios'!$K23+0.1),10) -> 2060 | P23: 45261 | Q23: =LEN(D23) -> 49 | R23: 30 | T23: =IFERROR(VLOOKUP(D23,BUSCARV!$A$1:$C$5524,2,0),"") | V23: =IF(U23="",T23,T23/U23) | W23: =IF(V23="","", IFERROR((V23-J23)/J23,"")) | Y23: =IFERROR(VLOOKUP(A23,#REF!,3,0),0) -> 0 | Z23: Desactivado
A24: 23 | B24: 12396254 | C24: Producto | D24: EXCELLENT KITTEN Present: 7,5kg | E24: Excellent | F24: Alimentos | G24: Gato | H24: =IF(J24="","",J24/1.21) -> 43636.364 | I24: 0.065 | J24: 52800 | K24: 0.33 | L24: =IF('Global Precios'!J24*(1-I24)*(1+'Global Precios'!K24)>10000,MROUND('Global Precios'!J24*(1-I24)*(1+'Global Precios'!K24),1000),MROUND('Global Precios'!J24*(1-I24)*(1+'Global Precios'!K24),500)) -> 66000 | M24: 7.5 | N24: kg | O24: =+MROUND(('Global Precios'!$J24/('Global Precios'!$M24))*(1+'Global Precios'!$K24+0.1),10) -> 10070 | P24: 45839 | Q24: =LEN(D24) -> 31 | R24: 30 | T24: =IFERROR(VLOOKUP(D24,BUSCARV!$A$1:$C$5524,2,0),"") | V24: =IF(U24="",T24,T24/U24) | W24: =IF(V24="","", IFERROR((V24-J24)/J24,"")) | Y24: =IFERROR(VLOOKUP(A24,#REF!,3,0),0) -> 0 | Z24: Activo
A25: 24 | B25: 12396142 | C25: Producto | D25: EXCELLENT ADULT CAT Present: 7,5kg | E25: Excellent | F25: Alimentos | G25: Gato | H25: =IF(J25="","",J25/1.21) -> 39421.488 | I25: 0.065 | J25: 47700 | K25: 0.33 | L25: =IF('Global Precios'!J25*(1-I25)*(1+'Global Precios'!K25)>10000,MROUND('Global Precios'!J25*(1-I25)*(1+'Global Precios'!K25),1000),MROUND('Global Precios'!J25*(1-I25)*(1+'Global Precios'!K25),500)) -> 59000 | M25: 7.5 | N25: kg | O25: =+MROUND(('Global Precios'!$J25/('Global Precios'!$M25))*(1+'Global Precios'!$K25+0.1),10) -> 9090 | P25: 45839 | Q25: =LEN(D25) -> 34 | R25: 30 | T25: =IFERROR(VLOOKUP(D25,BUSCARV!$A$1:$C$5524,2,0),"") | V25: =IF(U25="",T25,T25/U25) | W25: =IF(V25="","", IFERROR((V25-J25)/J25,"")) | Y25: =IFERROR(VLOOKUP(A25,#REF!,3,0),0) -> 0 | Z25: Activo
A26: 25 | B26: 12376707 | C26: Producto | D26: TIDY CATS Piedra Convencional 2KG | E26: Tidy Cats | F26: Pet-shop | H26: 435 | I26: 0.08 | J26: 1209 | K26: 0.5 | L26: =IF('Global Precios'!J26*(1-I26)*(1+'Global Precios'!K26)>1000,MROUND('Global Precios'!J26*(1-I26)*(1+'Global Precios'!K26),100),MROUND('Global Precios'!J26*(1-I26)*(1+'Global Precios'!K26),10)) -> 1700 | M26: 2 | N26: kg | P26: 45323 | Q26: =LEN(D26) -> 33 | R26: 30 | T26: =IFERROR(VLOOKUP(D26,BUSCARV!$A$1:$C$5524,2,0),"") | V26: =IF(U26="",T26,T26/U26) | W26: =IF(V26="","", IFERROR((V26-J26)/J26,"")) | Y26: =IFERROR(VLOOKUP(A26,#REF!,3,0),0) -> 0 | Z26: Desactivado
A27: 26 | B27: 12434296 | C27: Producto | D27: FELIX Sensaciones de Pez x sobre de 0.85 g | E27: Excellent | F27: Alimentos | G27: Gato | H27: =IF(J27="","",J27/1.21) -> 684.29752 | I27: 0.05 | J27: 828 | K27: 0.4 | L27: =IF('Global Precios'!J27*(1-I27)*(1+'Global Precios'!K27)>1000,MROUND('Global Precios'!J27*(1-I27)*(1+'Global Precios'!K27),100),MROUND('Global Precios'!J27*(1-I27)*(1+'Global Precios'!K27),10)) -> 1100 | M27: 0.85 | N27: kg | O27: - | P27: 45323 | Q27: =LEN(D27) -> 42 | R27: 30 | T27: =IFERROR(VLOOKUP(D27,BUSCARV!$A$1:$C$5524,2,0),"") | V27: =IF(U27="",T27,T27/U27) | W27: =IF(V27="","", IFERROR((V27-J27)/J27,"")) | Y27: =IFERROR(VLOOKUP(A27,#REF!,3,0),0) -> 0 | Z27: Desactivado
A28: 27 | B28: YPATT17 | C28: Producto | D28: YENU ADULTO(todos los t.) Present: 17kg | E28: YENU | F28: Alimentos | G28: Perro | H28: =IF(J28="","",J28/1.21) -> 3016.5289 | J28: 3650 | K28: 0.34 | L28: =IF('Global Precios'!J28*(1-I28)*(1+'Global Precios'!K28)>1000,MROUND('Global Precios'!J28*(1-I28)*(1+'Global Precios'!K28),100),MROUND('Global Precios'!J28*(1-I28)*(1+'Global Precios'!K28),10)) -> 4900 | M28: 17 | N28: kg | O28: =+MROUND(('Global Precios'!$J28/('Global Precios'!$M28))*(1+'Global Precios'!$K28+0.1),10) -> 310 | P28: 44986 | Q28: =LEN(D28) -> 39 | R28: 0 | T28: =IFERROR(VLOOKUP(D28,BUSCARV!$A$1:$C$5524,2,0),"") | V28: =IF(U28="",T28,T28/U28) | W28: =IF(V28="","", IFERROR((V28-J28)/J28,"")) | Y28: =IFERROR(VLOOKUP(A28,#REF!,3,0),0) -> 0 | Z28: Desactivado
A29: 28 | B29: YPAMP3 | C29: Producto | D29: YENU ADULTO M.P Present: 3kg | E29: YENU | F29: Alimentos | G29: Perro | H29: =IF(J29="","",J29/1.21) -> 826.44628 | J29: 1000 | K29: 0.34 | L29: =IF('Global Precios'!J29*(1-I29)*(1+'Global Precios'!K29)>1000,MROUND('Global Precios'!J29*(1-I29)*(1+'Global Precios'!K29),100),MROUND('Global Precios'!J29*(1-I29)*(1+'Global Precios'!K29),10)) -> 1300 | M29: 3 | N29: kg | O29: - | P29: 44986 | Q29: =LEN(D29) -> 28 | R29: 0 | T29: =IFERROR(VLOOKUP(D29,BUSCARV!$A$1:$C$5524,2,0),"") | V29: =IF(U29="",T29,T29/U29) | W29: =IF(V29="","", IFERROR((V29-J29)/J29,"")) | Y29: =IFERROR(VLOOKUP(A29,#REF!,3,0),0) -> 0 | Z29: Desactivado
A30: 29 | B30: YPCTT10 | C30: Producto | D30: YENU CACHORROS(todos los t) Present: 10kg | E30: YENU | F30: Alimentos | G30: Perro | H30: =IF(J30="","",J30/1.21) -> 2190.0826 | J30: 2650 | K30: 0.34 | L30: =IF('Global Precios'!J30*(1-I30)*(1+'Global Precios'!K30)>1000,MROUND('Global Precios'!J30*(1-I30)*(1+'Global Precios'!K30),100),MROUND('Global Precios'!J30*(1-I30)*(1+'Global Precios'!K30),10)) -> 3600 | M30: 10 | N30: kg | O30: =+MROUND(('Global Precios'!$J30/('Global Precios'!$M30))*(1+'Global Precios'!$K30+0.1),10) -> 380 | P30: 44986 | Q30: =LEN(D30) -> 41 | R30: 0 | T30: =IFERROR(VLOOKUP(D30,BUSCARV!$A$1:$C$5524,2,0),"") | V30: =IF(U30="",T30,T30/U30) | W30: =IF(V30="","", IFERROR((V30-J30)/J30,"")) | Y30: =IFERROR(VLOOKUP(A30,#REF!,3,0),0) -> 0 | Z30: Desactivado
A31: 30 | B31: YPCMP3 | C31: Producto | D31: YENU CACHORROS M.P Present: 3kg | E31: YENU | F31: Alimentos | G31: Perro | H31: =IF(J31="","",J31/1.21) -> 867.7686 | J31: 1050 | K31: 0.34 | L31: =IF('Global Precios'!J31*(1-I31)*(1+'Global Precios'!K31)>1000,MROUND('Global Precios'!J31*(1-I31)*(1+'Global Precios'!K31),100),MROUND('Global Precios'!J31*(1-I31)*(1+'Global Precios'!K31),10)) -> 1400 | M31: 3 | N31: kg | O31: - | P31: 44986 | Q31: =LEN(D31) -> 31 | R31: 0 | T31: =IFERROR(VLOOKUP(D31,BUSCARV!$A$1:$C$5524,2,0),"") | V31: =IF(U31="",T31,T31/U31) | W31: =IF(V31="","", IFERROR((V31-J31)/J31,"")) | Y31: =IFERROR(VLOOKUP(A31,#REF!,3,0),0) -> 0 | Z31: Desactivado
A32: 31 | B32: YGA7 | C32: Producto | D32: YENU GATOS ADULTOS Present: 7,5kg | E32: YENU | F32: Alimentos | G32: Gato | H32: =IF(J32="","",J32/1.21) -> 2438.0165 | J32: 2950 | K32: 0.34 | L32: =IF('Global Precios'!J32*(1-I32)*(1+'Global Precios'!K32)>1000,MROUND('Global Precios'!J32*(1-I32)*(1+'Global Precios'!K32),100),MROUND('Global Precios'!J32*(1-I32)*(1+'Global Precios'!K32),10)) -> 4000 | M32: 7.5 | N32: kg | O32: =+MROUND(('Global Precios'!$J32/('Global Precios'!$M32))*(1+'Global Precios'!$K32+0.1),10) -> 570 | P32: 44986 | Q32: =LEN(D32) -> 33 | R32: 0 | T32: =IFERROR(VLOOKUP(D32,BUSCARV!$A$1:$C$5524,2,0),"") | V32: =IF(U32="",T32,T32/U32) | W32: =IF(V32="","", IFERROR((V32-J32)/J32,"")) | Y32: =IFERROR(VLOOKUP(A32,#REF!,3,0),0) -> 0 | Z32: Desactivado
A33: 32 | B33: YGC7 | C33: Producto | D33: YENU GATOS CACHORROS Present: 7,5kg | E33: YENU | F33: Alimentos | G33: Gato | H33: =IF(J33="","",J33/1.21) -> 2619.8347 | J33: 3170 | K33: 0.34 | L33: =IF('Global Precios'!J33*(1-I33)*(1+'Global Precios'!K33)>1000,MROUND('Global Precios'!J33*(1-I33)*(1+'Global Precios'!K33),100),MROUND('Global Precios'!J33*(1-I33)*(1+'Global Precios'!K33),10)) -> 4200 | M33: 7.5 | N33: kg | O33: =+MROUND(('Global Precios'!$J33/('Global Precios'!$M33))*(1+'Global Precios'!$K33+0.1),10) -> 610 | P33: 44986 | Q33: =LEN(D33) -> 35 | R33: 0 | T33: =IFERROR(VLOOKUP(D33,BUSCARV!$A$1:$C$5524,2,0),"") | V33: =IF(U33="",T33,T33/U33) | W33: =IF(V33="","", IFERROR((V33-J33)/J33,"")) | Y33: =IFERROR(VLOOKUP(A33,#REF!,3,0),0) -> 0 | Z33: Desactivado
A34: 33 | C34: Producto | D34: AGILITY ADULTO Present: 15kg | E34: Agility | F34: Alimentos | G34: Perro | H34: =IF(J34="","",J34/1.21) -> 7423.9669 | J34: 8983 | K34: 0.33 | L34: =IF('Global Precios'!J34*(1-I34)*(1+'Global Precios'!K34)>1000,MROUND('Global Precios'!J34*(1-I34)*(1+'Global Precios'!K34),100),MROUND('Global Precios'!J34*(1-I34)*(1+'Global Precios'!K34),10)) -> 11900 | M34: 15 | N34: kg | O34: - | P34: 45139 | Q34: =LEN(D34) -> 28 | R34: 30 | T34: =IFERROR(VLOOKUP(D34,BUSCARV!$A$1:$C$5524,2,0),"") | V34: =IF(U34="",T34,T34/U34) | W34: =IF(V34="","", IFERROR((V34-J34)/J34,"")) | Y34: =IFERROR(VLOOKUP(A34,#REF!,3,0),0) -> 0 | Z34: Desactivado
A35: 34 | C35: Producto | D35: AGILITY ADULTO Present: 20kg | E35: Agility | F35: Alimentos | G35: Perro | H35: =IF(J35="","",J35/1.21) -> 8347.1074 | J35: 10100 | K35: 0.33 | L35: =IF('Global Precios'!J35*(1-I35)*(1+'Global Precios'!K35)>1000,MROUND('Global Precios'!J35*(1-I35)*(1+'Global Precios'!K35),100),MROUND('Global Precios'!J35*(1-I35)*(1+'Global Precios'!K35),10)) -> 13400 | M35: 20 | N35: kg | O35: =+MROUND(('Global Precios'!$J35/('Global Precios'!$M35))*(1+'Global Precios'!$K35+0.1),10) -> 720 | P35: 45108 | Q35: =LEN(D35) -> 28 | R35: 30 | T35: =IFERROR(VLOOKUP(D35,BUSCARV!$A$1:$C$5524,2,0),"") | V35: =IF(U35="",T35,T35/U35) | W35: =IF(V35="","", IFERROR((V35-J35)/J35,"")) | Y35: =IFERROR(VLOOKUP(A35,#REF!,3,0),0) -> 0 | Z35: Desactivado
A36: 35 | C36: Producto | D36: AGILITY CACHORROS Present: 15kg | E36: Agility | F36: Alimentos | G36: Perro | H36: =IF(J36="","",J36/1.21) -> 7589.2562 | J36: 9183 | K36: 0.33 | L36: =IF('Global Precios'!J36*(1-I36)*(1+'Global Precios'!K36)>1000,MROUND('Global Precios'!J36*(1-I36)*(1+'Global Precios'!K36),100),MROUND('Global Precios'!J36*(1-I36)*(1+'Global Precios'!K36),10)) -> 12200 | M36: 15 | N36: kg | O36: - | P36: 45108 | Q36: =LEN(D36) -> 31 | R36: 30 | T36: =IFERROR(VLOOKUP(D36,BUSCARV!$A$1:$C$5524,2,0),"") | V36: =IF(U36="",T36,T36/U36) | W36: =IF(V36="","", IFERROR((V36-J36)/J36,"")) | Y36: =IFERROR(VLOOKUP(A36,#REF!,3,0),0) -> 0 | Z36: Desactivado
A37: 36 | C37: Producto | D37: AGILITY CACHORROS Present: 20kg | E37: Agility | F37: Alimentos | G37: Perro | H37: =IF(J37="","",J37/1.21) -> 9628.0992 | J37: 11650 | K37: 0.33 | L37: =IF('Global Precios'!J37*(1-I37)*(1+'Global Precios'!K37)>1000,MROUND('Global Precios'!J37*(1-I37)*(1+'Global Precios'!K37),100),MROUND('Global Precios'!J37*(1-I37)*(1+'Global Precios'!K37),10)) -> 15500 | M37: 20 | N37: kg | O37: =+MROUND(('Global Precios'!$J37/('Global Precios'!$M37))*(1+'Global Precios'!$K37+0.1),10) -> 830 | P37: 45108 | Q37: =LEN(D37) -> 31 | R37: 30 | T37: =IFERROR(VLOOKUP(D37,BUSCARV!$A$1:$C$5524,2,0),"") | V37: =IF(U37="",T37,T37/U37) | W37: =IF(V37="","", IFERROR((V37-J37)/J37,"")) | Y37: =IFERROR(VLOOKUP(A37,#REF!,3,0),0) -> 0 | Z37: Desactivado
A38: 37 | C38: Producto | D38: AGILITY CATS ADULTO Present: 10kg | E38: Agility | F38: Alimentos | G38: Gato | H38: =IF(J38="","",J38/1.21) -> 19504.132 | J38: 23600 | K38: 0.33 | L38: =IF('Global Precios'!J38*(1-I38)*(1+'Global Precios'!K38)>1000,MROUND('Global Precios'!J38*(1-I38)*(1+'Global Precios'!K38),100),MROUND('Global Precios'!J38*(1-I38)*(1+'Global Precios'!K38),10)) -> 31400 | M38: 10 | N38: kg | O38: =+MROUND(('Global Precios'!$J38/('Global Precios'!$M38))*(1+'Global Precios'!$K38+0.1),10) -> 3370 | P38: 45323 | Q38: =LEN(D38) -> 33 | R38: 30 | T38: =IFERROR(VLOOKUP(D38,BUSCARV!$A$1:$C$5524,2,0),"") | V38: =IF(U38="",T38,T38/U38) | W38: =IF(V38="","", IFERROR((V38-J38)/J38,"")) | Y38: =IFERROR(VLOOKUP(A38,#REF!,3,0),0) -> 0 | Z38: Desactivado
A39: 38 | C39: Producto | D39: AGILITY CATS KITTEN Present: 10kg | E39: Agility | F39: Alimentos | G39: Gato | H39: =IF(J39="","",J39/1.21) -> 8529.7521 | J39: 10321 | K39: 0.33 | L39: =IF('Global Precios'!J39*(1-I39)*(1+'Global Precios'!K39)>1000,MROUND('Global Precios'!J39*(1-I39)*(1+'Global Precios'!K39),100),MROUND('Global Precios'!J39*(1-I39)*(1+'Global Precios'!K39),10)) -> 13700 | M39: 10 | N39: kg | O39: =+MROUND(('Global Precios'!$J39/('Global Precios'!$M39))*(1+'Global Precios'!$K39+0.1),10) -> 1480 | P39: 45108 | Q39: =LEN(D39) -> 33 | R39: 30 | T39: =IFERROR(VLOOKUP(D39,BUSCARV!$A$1:$C$5524,2,0),"") | V39: =IF(U39="",T39,T39/U39) | W39: =IF(V39="","", IFERROR((V39-J39)/J39,"")) | Y39: =IFERROR(VLOOKUP(A39,#REF!,3,0),0) -> 0 | Z39: Desactivado
A40: 39 | C40: Producto | D40: DENTAL PLAX X 250 ML | E40: AFFORD | F40: Medicamentos | G40: VITAMINAS Y PROT. HEPATICOS,ETC | H40: =IF(J40="","",J40/1.21) -> 2644.6281 | J40: 3200 | K40: 0.8 | L40: =IF('Global Precios'!J40*(1-I40)*(1+'Global Precios'!K40)>10000,MROUND('Global Precios'!J40*(1-I40)*(1+'Global Precios'!K40),1000),MROUND('Global Precios'!J40*(1-I40)*(1+'Global Precios'!K40),500)) -> 6000 | M40: 250 | N40: ml | P40: 46082 | Q40: =LEN(D40) -> 20 | R40: 30 | T40: =IFERROR(VLOOKUP(D40,BUSCARV!$A$1:$C$5524,2,0),"") -> 2723 | V40: =IF(U40="",T40,T40/U40) -> 2723 | W40: =IF(V40="","", IFERROR((V40-J40)/J40,"")) -> -0.1490625 | Y40: =IFERROR(VLOOKUP(A40,#REF!,3,0),0) -> 0 | Z40: Activo
A41: 40 | C41: Producto | D41: EXPECTORANTE X 100 ML (LAIKA) | E41: ALLIGNANI HNOS P.A. | F41: Medicamentos | G41: VITAMINAS Y PROT. HEPATICOS,ETC | H41: =IF(J41="","",J41/1.21) -> 4921.4876 | J41: 5955 | K41: 0.8 | L41: =IF('Global Precios'!J41*(1-I41)*(1+'Global Precios'!K41)>10000,MROUND('Global Precios'!J41*(1-I41)*(1+'Global Precios'!K41),1000),MROUND('Global Precios'!J41*(1-I41)*(1+'Global Precios'!K41),500)) -> 11000 | M41: 100 | N41: ml | P41: 45839 | Q41: =LEN(D41) -> 29 | R41: 30 | T41: =IFERROR(VLOOKUP(D41,BUSCARV!$A$1:$C$5524,2,0),"") -> 5955 | V41: =IF(U41="",T41,T41/U41) -> 5955 | W41: =IF(V41="","", IFERROR((V41-J41)/J41,"")) -> 0 | Y41: =IFERROR(VLOOKUP(A41,#REF!,3,0),0) -> 0 | Z41: Activo
A42: 41 | C42: Producto | D42: KILL AG X 440 ML | E42: BROUWER PA | F42: Medicamentos | G42: CREMAS | H42: =IF(J42="","",J42/1.21) -> 4880.1653 | J42: 5905 | K42: 1 | L42: =IF('Global Precios'!J42*(1-I42)*(1+'Global Precios'!K42)>10000,MROUND('Global Precios'!J42*(1-I42)*(1+'Global Precios'!K42),1000),MROUND('Global Precios'!J42*(1-I42)*(1+'Global Precios'!K42),500)) -> 12000 | P42: 45839 | Q42: =LEN(D42) -> 16 | R42: 30 | T42: =IFERROR(VLOOKUP(D42,BUSCARV!$A$1:$C$5524,2,0),"") -> 5905 | V42: =IF(U42="",T42,T42/U42) -> 5905 | W42: =IF(V42="","", IFERROR((V42-J42)/J42,"")) -> 0 | Y42: =IFERROR(VLOOKUP(A42,#REF!,3,0),0) -> 0 | Z42: Activo
A43: 42 | C43: Producto | D43: LAXAVET X 40 GR | E43: BROUWER PA | F43: Medicamentos | G43: VITAMINAS Y PROT. HEPATICOS,ETC | H43: =IF(J43="","",J43/1.21) -> 6772.7273 | J43: 8195 | K43: 0.8 | L43: =IF('Global Precios'!J43*(1-I43)*(1+'Global Precios'!K43)>10000,MROUND('Global Precios'!J43*(1-I43)*(1+'Global Precios'!K43),1000),MROUND('Global Precios'!J43*(1-I43)*(1+'Global Precios'!K43),500)) -> 15000 | M43: 40 | N43: grs | P43: 45839 | Q43: =LEN(D43) -> 15 | R43: 30 | T43: =IFERROR(VLOOKUP(D43,BUSCARV!$A$1:$C$5524,2,0),"") -> 8195 | V43: =IF(U43="",T43,T43/U43) -> 8195 | W43: =IF(V43="","", IFERROR((V43-J43)/J43,"")) -> 0 | Y43: =IFERROR(VLOOKUP(A43,#REF!,3,0),0) -> 0 | Z43: Activo
A44: 43 | C44: Producto | D44: FORTIPET ELMER | E44: ELMER P.A | F44: Medicamentos | G44: VITAMINAS Y PROT. HEPATICOS,ETC | H44: =IF(J44="","",J44/1.21) -> 4348.7603 | J44: 5262 | K44: 0.8 | L44: =IF('Global Precios'!J44*(1-I44)*(1+'Global Precios'!K44)>1000,MROUND('Global Precios'!J44*(1-I44)*(1+'Global Precios'!K44),100),MROUND('Global Precios'!J44*(1-I44)*(1+'Global Precios'!K44),10)) -> 9500 | P44: 45383 | Q44: =LEN(D44) -> 14 | R44: 30 | T44: =IFERROR(VLOOKUP(D44,BUSCARV!$A$1:$C$5524,2,0),"") -> 7705 | V44: =IF(U44="",T44,T44/U44) -> 7705 | W44: =IF(V44="","", IFERROR((V44-J44)/J44,"")) -> 0.46427214 | Y44: =IFERROR(VLOOKUP(A44,#REF!,3,0),0) -> 0 | Z44: Desactivado
A45: 44 | C45: Producto | D45: ECTHOL 5 AP X 70 ML | E45: HOLLIDAY | F45: Medicamentos | G45: LIQUIDOS Y SHAMPOOS | H45: =IF(J45="","",J45/1.21) -> 3366.1157 | J45: 4073 | K45: 0.8 | L45: =IF('Global Precios'!J45*(1-I45)*(1+'Global Precios'!K45)>10000,MROUND('Global Precios'!J45*(1-I45)*(1+'Global Precios'!K45),1000),MROUND('Global Precios'!J45*(1-I45)*(1+'Global Precios'!K45),500)) -> 7500 | M45: 70 | N45: ml | P45: 45839 | Q45: =LEN(D45) -> 19 | R45: 30 | T45: =IFERROR(VLOOKUP(D45,BUSCARV!$A$1:$C$5524,2,0),"") -> 4073 | V45: =IF(U45="",T45,T45/U45) -> 4073 | W45: =IF(V45="","", IFERROR((V45-J45)/J45,"")) -> 0 | Y45: =IFERROR(VLOOKUP(A45,#REF!,3,0),0) -> 0 | Z45: Activo
A46: 45 | C46: Producto | D46: ECTHOL 5 AP X 120 ML | E46: HOLLIDAY | F46: Medicamentos | G46: LIQUIDOS Y SHAMPOOS | H46: =IF(J46="","",J46/1.21) -> 4745.4545 | J46: 5742 | K46: 0.8 | L46: =IF('Global Precios'!J46*(1-I46)*(1+'Global Precios'!K46)>10000,MROUND('Global Precios'!J46*(1-I46)*(1+'Global Precios'!K46),1000),MROUND('Global Precios'!J46*(1-I46)*(1+'Global Precios'!K46),500)) -> 10000 | M46: 120 | N46: ml | P46: 45839 | Q46: =LEN(D46) -> 20 | R46: 30 | T46: =IFERROR(VLOOKUP(D46,BUSCARV!$A$1:$C$5524,2,0),"") -> 5742 | V46: =IF(U46="",T46,T46/U46) -> 5742 | W46: =IF(V46="","", IFERROR((V46-J46)/J46,"")) -> 0 | Y46: =IFERROR(VLOOKUP(A46,#REF!,3,0),0) -> 0 | Z46: Activo
A47: 46 | C47: Producto | D47: PREDNISOLONA PYO 10 X 100 COMPRIMIDOS | E47: IDV | F47: Medicamentos | G47: ANTIIINFLAMATORIOS Y ANALGÉSICOS | H47: =IF(J47="","",J47/1.21) -> 0 | J47: 0 | K47: 1 | L47: =IF('Global Precios'!J47*(1-I47)*(1+'Global Precios'!K47)>1000,MROUND('Global Precios'!J47*(1-I47)*(1+'Global Precios'!K47),100),MROUND('Global Precios'!J47*(1-I47)*(1+'Global Precios'!K47),10)) -> 0 | M47: 0.01 | P47: 45261 | Q47: =LEN(D47) -> 37 | R47: 0 | T47: =IFERROR(VLOOKUP(D47,BUSCARV!$A$1:$C$5524,2,0),"") -> 12415 | V47: =IF(U47="",T47,T47/U47) -> 12415 | W47: =IF(V47="","", IFERROR((V47-J47)/J47,"")) | Y47: =IFERROR(VLOOKUP(A47,#REF!,3,0),0) -> 0 | Z47: Desactivado
A48: 47 | C48: Producto | D48: PREDNISOLONA PYO 20 X BLISTER 10 COMPRIMIDOS | E48: IDV | F48: Medicamentos | G48: ANTIIINFLAMATORIOS Y ANALGÉSICOS | H48: =IF(J48="","",J48/1.21) -> 1500 | J48: 1815 | K48: 1 | L48: =IF('Global Precios'!J48*(1-I48)*(1+'Global Precios'!K48)>10000,MROUND('Global Precios'!J48*(1-I48)*(1+'Global Precios'!K48),1000),MROUND('Global Precios'!J48*(1-I48)*(1+'Global Precios'!K48),500)) -> 3500 | M48: 10 | N48: Comprimidos | P48: 45901 | Q48: =LEN(D48) -> 44 | R48: 30 | T48: =IFERROR(VLOOKUP(D48,BUSCARV!$A$1:$C$5524,2,0),"") | V48: =IF(U48="",T48,T48/U48) | W48: =IF(V48="","", IFERROR((V48-J48)/J48,"")) | Y48: =IFERROR(VLOOKUP(A48,#REF!,3,0),0) -> 0 | Z48: Activo
A49: 48 | C49: Producto | D49: PYO DERM 125 X BLISTER 10 COMP | E49: IDV | F49: Medicamentos | G49: ANTIBIÓTICOS | H49: =IF(J49="","",J49/1.21) -> 995.04132 | J49: 1204 | K49: 1 | L49: =IF('Global Precios'!J49*(1-I49)*(1+'Global Precios'!K49)>10000,MROUND('Global Precios'!J49*(1-I49)*(1+'Global Precios'!K49),1000),MROUND('Global Precios'!J49*(1-I49)*(1+'Global Precios'!K49),500)) -> 2500 | M49: 10 | N49: Comprimidos | P49: 45901 | Q49: =LEN(D49) -> 30 | R49: 30 | T49: =IFERROR(VLOOKUP(D49,BUSCARV!$A$1:$C$5524,2,0),"") | V49: =IF(U49="",T49,T49/U49) | W49: =IF(V49="","", IFERROR((V49-J49)/J49,"")) | Y49: =IFERROR(VLOOKUP(A49,#REF!,3,0),0) -> 0 | Z49: Activo
A50: 49 | C50: Producto | D50: PYO DERM 500 X BLISTER x 10 COMP | E50: IDV | F50: Medicamentos | G50: ANTIBIÓTICOS | H50: =IF(J50="","",J50/1.21) -> 2272.7273 | J50: 2750 | K50: 1 | L50: =IF('Global Precios'!J50*(1-I50)*(1+'Global Precios'!K50)>10000,MROUND('Global Precios'!J50*(1-I50)*(1+'Global Precios'!K50),1000),MROUND('Global Precios'!J50*(1-I50)*(1+'Global Precios'!K50),500)) -> 5500 | M50: 10 | N50: Comprimidos | P50: 45901 | Q50: =LEN(D50) -> 32 | R50: 30 | T50: =IFERROR(VLOOKUP(D50,BUSCARV!$A$1:$C$5524,2,0),"") | V50: =IF(U50="",T50,T50/U50) | W50: =IF(V50="","", IFERROR((V50-J50)/J50,"")) | Y50: =IFERROR(VLOOKUP(A50,#REF!,3,0),0) -> 0 | Z50: Activo
A51: 50 | C51: Producto | D51: OTOVIER "NF" X 25 ML | E51: JANVIER | F51: Medicamentos | G51: OIDOS | H51: =IF(J51="","",J51/1.21) -> 3817.3554 | J51: 4619 | K51: 0.8 | L51: =IF('Global Precios'!J51*(1-I51)*(1+'Global Precios'!K51)>10000,MROUND('Global Precios'!J51*(1-I51)*(1+'Global Precios'!K51),1000),MROUND('Global Precios'!J51*(1-I51)*(1+'Global Precios'!K51),500)) -> 8500 | M51: 25 | N51: ml | P51: 45839 | Q51: =LEN(D51) -> 20 | R51: 30 | T51: =IFERROR(VLOOKUP(D51,BUSCARV!$A$1:$C$5524,2,0),"") -> 4619 | V51: =IF(U51="",T51,T51/U51) -> 4619 | W51: =IF(V51="","", IFERROR((V51-J51)/J51,"")) -> 0 | Y51: =IFERROR(VLOOKUP(A51,#REF!,3,0),0) -> 0 | Z51: Activo
A52: 51 | C52: Producto | D52: OTOVIER SOLUCION LIMPIA OREJAS X 120 ML | E52: JANVIER | F52: Medicamentos | G52: OIDOS | H52: =IF(J52="","",J52/1.21) -> 2604.1322 | J52: 3151 | K52: 0.8 | L52: =IF('Global Precios'!J52*(1-I52)*(1+'Global Precios'!K52)>1000,MROUND('Global Precios'!J52*(1-I52)*(1+'Global Precios'!K52),100),MROUND('Global Precios'!J52*(1-I52)*(1+'Global Precios'!K52),10)) -> 5700 | M52: 120 | N52: ml | P52: 45505 | Q52: =LEN(D52) -> 39 | R52: 30 | T52: =IFERROR(VLOOKUP(D52,BUSCARV!$A$1:$C$5524,2,0),"") | V52: =IF(U52="",T52,T52/U52) | W52: =IF(V52="","", IFERROR((V52-J52)/J52,"")) | Y52: =IFERROR(VLOOKUP(A52,#REF!,3,0),0) -> 0 | Z52: Desactivado
A53: 52 | C53: Producto | D53: OTOVIER SOLUCION LIMPIA OREJAS X 40 ML | E53: JANVIER | F53: Medicamentos | G53: OIDOS | H53: =IF(J53="","",J53/1.21) -> 3060.3306 | J53: 3703 | K53: 0.8 | L53: =IF('Global Precios'!J53*(1-I53)*(1+'Global Precios'!K53)>10000,MROUND('Global Precios'!J53*(1-I53)*(1+'Global Precios'!K53),1000),MROUND('Global Precios'!J53*(1-I53)*(1+'Global Precios'!K53),500)) -> 6500 | M53: 40 | N53: ml | P53: 45839 | Q53: =LEN(D53) -> 38 | R53: 30 | T53: =IFERROR(VLOOKUP(D53,BUSCARV!$A$1:$C$5524,2,0),"") -> 3703 | V53: =IF(U53="",T53,T53/U53) -> 3703 | W53: =IF(V53="","", IFERROR((V53-J53)/J53,"")) -> 0 | Y53: =IFERROR(VLOOKUP(A53,#REF!,3,0),0) -> 0 | Z53: Activo
A54: 53 | C54: Producto | D54: COLOTRIN PALATABLE BLISTER X 6 COM | E54: JOHN MARTIN | F54: Medicamentos | G54: VITAMINAS Y PROT. HEPATICOS,ETC | H54: =IF(J54="","",J54/1.21) -> 2281.8182 | J54: 2761 | K54: 0.8 | L54: =IF('Global Precios'!J54*(1-I54)*(1+'Global Precios'!K54)>1000,MROUND('Global Precios'!J54*(1-I54)*(1+'Global Precios'!K54),100),MROUND('Global Precios'!J54*(1-I54)*(1+'Global Precios'!K54),10)) -> 5000 | M54: 10 | N54: Comprimidos | P54: 45413 | Q54: =LEN(D54) -> 34 | R54: 30 | T54: =IFERROR(VLOOKUP(D54,BUSCARV!$A$1:$C$5524,2,0),"") | V54: =IF(U54="",T54,T54/U54) | W54: =IF(V54="","", IFERROR((V54-J54)/J54,"")) | Y54: =IFERROR(VLOOKUP(A54,#REF!,3,0),0) -> 0 | Z54: Desactivado
A55: 54 | C55: Producto | D55: COMPLEJO VITAMINICO JM X 100 ML | E55: JOHN MARTIN | F55: Medicamentos | G55: VITAMINAS Y PROT. HEPATICOS,ETC | H55: =IF(J55="","",J55/1.21) -> 4876.0331 | J55: 5900 | K55: 0.8 | L55: =IF('Global Precios'!J55*(1-I55)*(1+'Global Precios'!K55)>10000,MROUND('Global Precios'!J55*(1-I55)*(1+'Global Precios'!K55),1000),MROUND('Global Precios'!J55*(1-I55)*(1+'Global Precios'!K55),500)) -> 11000 | M55: 100 | N55: ml | P55: 46082 | Q55: =LEN(D55) -> 31 | R55: 30 | T55: =IFERROR(VLOOKUP(D55,BUSCARV!$A$1:$C$5524,2,0),"") -> 4167 | V55: =IF(U55="",T55,T55/U55) -> 4167 | W55: =IF(V55="","", IFERROR((V55-J55)/J55,"")) -> -0.29372881 | Y55: =IFERROR(VLOOKUP(A55,#REF!,3,0),0) -> 0 | Z55: Activo
A56: 55 | C56: Producto | D56: HEPATOPROTECTOR JM X 15 ML | E56: JOHN MARTIN | F56: Medicamentos | G56: VITAMINAS Y PROT. HEPATICOS,ETC | H56: =IF(J56="","",J56/1.21) -> 3454.5455 | J56: 4180 | K56: 0.8 | L56: =IF('Global Precios'!J56*(1-I56)*(1+'Global Precios'!K56)>10000,MROUND('Global Precios'!J56*(1-I56)*(1+'Global Precios'!K56),1000),MROUND('Global Precios'!J56*(1-I56)*(1+'Global Precios'!K56),500)) -> 7500 | M56: 15 | N56: ml | P56: 45839 | Q56: =LEN(D56) -> 26 | R56: 30 | T56: =IFERROR(VLOOKUP(D56,BUSCARV!$A$1:$C$5524,2,0),"") -> 4431 | V56: =IF(U56="",T56,T56/U56) -> 4431 | W56: =IF(V56="","", IFERROR((V56-J56)/J56,"")) -> 0.060047847 | Y56: =IFERROR(VLOOKUP(A56,#REF!,3,0),0) -> 0 | Z56: Desactivado
A57: 56 | C57: Producto | D57: MELOXIVET COMPRIMIDO X 1 COMP | E57: JOHN MARTIN | F57: Medicamentos | G57: ANTIIINFLAMATORIOS Y ANALGÉSICOS | H57: =IF(J57="","",J57/1.21) -> 330.57851 | J57: 400 | K57: 1 | L57: =IF('Global Precios'!J57*(1-I57)*(1+'Global Precios'!K57)>10000,MROUND('Global Precios'!J57*(1-I57)*(1+'Global Precios'!K57),1000),MROUND('Global Precios'!J57*(1-I57)*(1+'Global Precios'!K57),500)) -> 1000 | M57: 1 | N57: Comprimidos | P57: 45839 | Q57: =LEN(D57) -> 29 | R57: 30 | T57: =IFERROR(VLOOKUP(D57,BUSCARV!$A$1:$C$5524,2,0),"") | V57: =IF(U57="",T57,T57/U57) | W57: =IF(V57="","", IFERROR((V57-J57)/J57,"")) | Y57: =IFERROR(VLOOKUP(A57,#REF!,3,0),0) -> 0 | Z57: Activo
A58: 57 | C58: Producto | D58: MELOXIVET GOTAS X 10 ML | E58: JOHN MARTIN | F58: Medicamentos | G58: ANTIIINFLAMATORIOS Y ANALGÉSICOS | H58: =IF(J58="","",J58/1.21) -> 6287.6033 | J58: 7608 | K58: 0.8 | L58: =IF('Global Precios'!J58*(1-I58)*(1+'Global Precios'!K58)>10000,MROUND('Global Precios'!J58*(1-I58)*(1+'Global Precios'!K58),1000),MROUND('Global Precios'!J58*(1-I58)*(1+'Global Precios'!K58),500)) -> 14000 | M58: 10 | N58: ml | P58: 45839 | Q58: =LEN(D58) -> 23 | R58: 30 | T58: =IFERROR(VLOOKUP(D58,BUSCARV!$A$1:$C$5524,2,0),"") -> 7608 | V58: =IF(U58="",T58,T58/U58) -> 7608 | W58: =IF(V58="","", IFERROR((V58-J58)/J58,"")) -> 0 | Y58: =IFERROR(VLOOKUP(A58,#REF!,3,0),0) -> 0 | Z58: Activo
A59: 58 | C59: Producto | D59: NUTRIPET PALATABLE X 40 GRS | E59: JOHN MARTIN | F59: Medicamentos | G59: VITAMINAS Y PROT. HEPATICOS,ETC | H59: =IF(J59="","",J59/1.21) -> 3416.5289 | J59: 4134 | K59: 0.8 | L59: =IF('Global Precios'!J59*(1-I59)*(1+'Global Precios'!K59)>10000,MROUND('Global Precios'!J59*(1-I59)*(1+'Global Precios'!K59),1000),MROUND('Global Precios'!J59*(1-I59)*(1+'Global Precios'!K59),500)) -> 7500 | M59: 40 | N59: grs | P59: 45839 | Q59: =LEN(D59) -> 27 | R59: 30 | T59: =IFERROR(VLOOKUP(D59,BUSCARV!$A$1:$C$5524,2,0),"") -> 4134 | V59: =IF(U59="",T59,T59/U59) -> 4134 | W59: =IF(V59="","", IFERROR((V59-J59)/J59,"")) -> 0 | Y59: =IFERROR(VLOOKUP(A59,#REF!,3,0),0) -> 0 | Z59: Activo
A60: 59 | C60: Producto | D60: TRAMADOL HOSPITALARIO X BLISTER X 10 COMP | E60: JOHN MARTIN | F60: Medicamentos | G60: ANTIIINFLAMATORIOS Y ANALGÉSICOS | H60: =IF(J60="","",J60/1.21) -> 1985.124 | J60: 2402 | K60: 1 | L60: =IF('Global Precios'!J60*(1-I60)*(1+'Global Precios'!K60)>1000,MROUND('Global Precios'!J60*(1-I60)*(1+'Global Precios'!K60),100),MROUND('Global Precios'!J60*(1-I60)*(1+'Global Precios'!K60),10)) -> 4800 | M60: 10 | N60: Comprimidos | P60: 45505 | Q60: =LEN(D60) -> 41 | R60: 30 | T60: =IFERROR(VLOOKUP(D60,BUSCARV!$A$1:$C$5524,2,0),"") | V60: =IF(U60="",T60,T60/U60) | W60: =IF(V60="","", IFERROR((V60-J60)/J60,"")) | Y60: =IFERROR(VLOOKUP(A60,#REF!,3,0),0) -> 0 | Z60: Desactivado
A61: 60 | C61: Producto | D61: DOMINAL MAX GATO HASTA 4 KG | E61: KONIG P.A | F61: Medicamentos | G61: PIPETAS | H61: =IF(J61="","",J61/1.21) -> 1686.7769 | J61: 2041 | K61: 0.8 | L61: =IF('Global Precios'!J61*(1-I61)*(1+'Global Precios'!K61)>10000,MROUND('Global Precios'!J61*(1-I61)*(1+'Global Precios'!K61),1000),MROUND('Global Precios'!J61*(1-I61)*(1+'Global Precios'!K61),500)) -> 3500 | M61: 1 | N61: Unidad | P61: 45839 | Q61: =LEN(D61) -> 27 | R61: 30 | T61: =IFERROR(VLOOKUP(D61,BUSCARV!$A$1:$C$5524,2,0),"") -> 2072 | V61: =IF(U61="",T61,T61/U61) -> 2072 | W61: =IF(V61="","", IFERROR((V61-J61)/J61,"")) -> 0.015188633 | Y61: =IFERROR(VLOOKUP(A61,#REF!,3,0),0) -> 0 | Z61: Desactivado
A62: 61 | C62: Producto | D62: DOMINAL MAX GATO MAS DE 4 KG | E62: KONIG P.A | F62: Medicamentos | G62: PIPETAS | H62: =IF(J62="","",J62/1.21) -> 1861.157 | J62: 2252 | K62: 0.8 | L62: =IF('Global Precios'!J62*(1-I62)*(1+'Global Precios'!K62)>10000,MROUND('Global Precios'!J62*(1-I62)*(1+'Global Precios'!K62),1000),MROUND('Global Precios'!J62*(1-I62)*(1+'Global Precios'!K62),500)) -> 4000 | M62: 1 | N62: Unidad | P62: 45839 | Q62: =LEN(D62) -> 28 | R62: 30 | T62: =IFERROR(VLOOKUP(D62,BUSCARV!$A$1:$C$5524,2,0),"") -> 2286 | V62: =IF(U62="",T62,T62/U62) -> 2286 | W62: =IF(V62="","", IFERROR((V62-J62)/J62,"")) -> 0.015097691 | Y62: =IFERROR(VLOOKUP(A62,#REF!,3,0),0) -> 0 | Z62: Desactivado
A63: 62 | C63: Producto | D63: DOMINAL MAX PERRO 5-10 KG | E63: KONIG P.A | F63: Medicamentos | G63: PIPETAS | H63: =IF(J63="","",J63/1.21) -> 2128.0992 | J63: 2575 | K63: 0.8 | L63: =IF('Global Precios'!J63*(1-I63)*(1+'Global Precios'!K63)>10000,MROUND('Global Precios'!J63*(1-I63)*(1+'Global Precios'!K63),1000),MROUND('Global Precios'!J63*(1-I63)*(1+'Global Precios'!K63),500)) -> 4500 | M63: 1 | N63: Unidad | P63: 45839 | Q63: =LEN(D63) -> 25 | R63: 30 | T63: =IFERROR(VLOOKUP(D63,BUSCARV!$A$1:$C$5524,2,0),"") -> 2575 | V63: =IF(U63="",T63,T63/U63) -> 2575 | W63: =IF(V63="","", IFERROR((V63-J63)/J63,"")) -> 0 | Y63: =IFERROR(VLOOKUP(A63,#REF!,3,0),0) -> 0 | Z63: Activo
A64: 63 | C64: Producto | D64: DOMINAL MAX PERRO HASTA 5 KG | E64: KONIG P.A | F64: Medicamentos | G64: PIPETAS | H64: =IF(J64="","",J64/1.21) -> 1957.8512 | J64: 2369 | K64: 0.8 | L64: =IF('Global Precios'!J64*(1-I64)*(1+'Global Precios'!K64)>10000,MROUND('Global Precios'!J64*(1-I64)*(1+'Global Precios'!K64),1000),MROUND('Global Precios'!J64*(1-I64)*(1+'Global Precios'!K64),500)) -> 4500 | M64: 1 | N64: Unidad | P64: 45839 | Q64: =LEN(D64) -> 28 | R64: 30 | T64: =IFERROR(VLOOKUP(D64,BUSCARV!$A$1:$C$5524,2,0),"") -> 2369 | V64: =IF(U64="",T64,T64/U64) -> 2369 | W64: =IF(V64="","", IFERROR((V64-J64)/J64,"")) -> 0 | Y64: =IFERROR(VLOOKUP(A64,#REF!,3,0),0) -> 0 | Z64: Activo
A65: 64 | C65: Producto | D65: EUTAZUM X 120 ML | E65: KONIG P.A | F65: Medicamentos | G65: VITAMINAS Y PROT. HEPATICOS,ETC | H65: =IF(J65="","",J65/1.21) -> 1718.1818 | J65: 2079 | K65: 0.8 | L65: =IF('Global Precios'!J65*(1-I65)*(1+'Global Precios'!K65)>1000,MROUND('Global Precios'!J65*(1-I65)*(1+'Global Precios'!K65),100),MROUND('Global Precios'!J65*(1-I65)*(1+'Global Precios'!K65),10)) -> 3700 | M65: 120 | N65: ml | P65: 45323 | Q65: =LEN(D65) -> 16 | R65: 30 | T65: =IFERROR(VLOOKUP(D65,BUSCARV!$A$1:$C$5524,2,0),"") | V65: =IF(U65="",T65,T65/U65) | W65: =IF(V65="","", IFERROR((V65-J65)/J65,"")) | Y65: =IFERROR(VLOOKUP(A65,#REF!,3,0),0) -> 0 | Z65: Desactivado
A66: 65 | C66: Producto | D66: ENROFLOXACINA KUALKOS 50 MG X Blister x 10 COMP | E66: KUALCOS | F66: Medicamentos | G66: ANTIBIÓTICOS | H66: =IF(J66="","",J66/1.21) -> 944.6281 | J66: 1143 | K66: 1 | L66: =IF('Global Precios'!J66*(1-I66)*(1+'Global Precios'!K66)>10000,MROUND('Global Precios'!J66*(1-I66)*(1+'Global Precios'!K66),1000),MROUND('Global Precios'!J66*(1-I66)*(1+'Global Precios'!K66),500)) -> 2500 | M66: 10 | N66: Comprimidos | P66: 45839 | Q66: =LEN(D66) -> 47 | R66: 30 | T66: =IFERROR(VLOOKUP(D66,BUSCARV!$A$1:$C$5524,2,0),"") | V66: =IF(U66="",T66,T66/U66) | W66: =IF(V66="","", IFERROR((V66-J66)/J66,"")) | Y66: =IFERROR(VLOOKUP(A66,#REF!,3,0),0) -> 0 | Z66: Activo
A67: 66 | C67: Producto | D67: KUALCODERM CREMA X 40 GRS | E67: KUALCOS | F67: Medicamentos | G67: CREMAS | H67: =IF(J67="","",J67/1.21) -> 5064.4628 | J67: 6128 | K67: 0.8 | L67: =IF('Global Precios'!J67*(1-I67)*(1+'Global Precios'!K67)>10000,MROUND('Global Precios'!J67*(1-I67)*(1+'Global Precios'!K67),1000),MROUND('Global Precios'!J67*(1-I67)*(1+'Global Precios'!K67),500)) -> 11000 | M67: 40 | N67: grs | P67: 45870 | Q67: =LEN(D67) -> 25 | R67: 30 | T67: =IFERROR(VLOOKUP(D67,BUSCARV!$A$1:$C$5524,2,0),"") -> 6128 | V67: =IF(U67="",T67,T67/U67) -> 6128 | W67: =IF(V67="","", IFERROR((V67-J67)/J67,"")) -> 0 | Y67: =IFERROR(VLOOKUP(A67,#REF!,3,0),0) -> 0 | Z67: Activo
A68: 67 | C68: Producto | D68: FELINE ENDOSPOT 02-05 KG | E68: LABYES | F68: Medicamentos | G68: ANTIPARASITARIOS INTERNOS | H68: =IF(J68="","",J68/1.21) -> 710.7438 | J68: 860 | K68: 0.8 | L68: =IF('Global Precios'!J68*(1-I68)*(1+'Global Precios'!K68)>1000,MROUND('Global Precios'!J68*(1-I68)*(1+'Global Precios'!K68),100),MROUND('Global Precios'!J68*(1-I68)*(1+'Global Precios'!K68),10)) -> 1500 | M68: 1 | N68: Unidad | P68: 45139 | Q68: =LEN(D68) -> 24 | R68: 30 | T68: =IFERROR(VLOOKUP(D68,BUSCARV!$A$1:$C$5524,2,0),"") | V68: =IF(U68="",T68,T68/U68) | W68: =IF(V68="","", IFERROR((V68-J68)/J68,"")) | Y68: =IFERROR(VLOOKUP(A68,#REF!,3,0),0) -> 0 | Z68: Desactivado
A69: 68 | C69: Producto | D69: FELINE ENDOSPOT MÁS DE 5 KG | E69: LABYES | F69: Medicamentos | G69: ANTIPARASITARIOS INTERNOS | H69: =IF(J69="","",J69/1.21) -> 763.63636 | J69: 924 | K69: 0.8 | L69: =IF('Global Precios'!J69*(1-I69)*(1+'Global Precios'!K69)>1000,MROUND('Global Precios'!J69*(1-I69)*(1+'Global Precios'!K69),100),MROUND('Global Precios'!J69*(1-I69)*(1+'Global Precios'!K69),10)) -> 1700 | M69: 1 | N69: Unidad | P69: 45139 | Q69: =LEN(D69) -> 27 | R69: 30 | T69: =IFERROR(VLOOKUP(D69,BUSCARV!$A$1:$C$5524,2,0),"") | V69: =IF(U69="",T69,T69/U69) | W69: =IF(V69="","", IFERROR((V69-J69)/J69,"")) | Y69: =IFERROR(VLOOKUP(A69,#REF!,3,0),0) -> 0 | Z69: Desactivado
A70: 69 | C70: Producto | D70: TAU CON ESTEROIDES X 10 ML | E70: LABYES | F70: Medicamentos | G70: OJOS | H70: =IF(J70="","",J70/1.21) -> 7267.7686 | J70: 8794 | K70: 0.8 | L70: =IF('Global Precios'!J70*(1-I70)*(1+'Global Precios'!K70)>10000,MROUND('Global Precios'!J70*(1-I70)*(1+'Global Precios'!K70),1000),MROUND('Global Precios'!J70*(1-I70)*(1+'Global Precios'!K70),500)) -> 16000 | M70: 10 | N70: ml | P70: 45839 | Q70: =LEN(D70) -> 26 | R70: 30 | T70: =IFERROR(VLOOKUP(D70,BUSCARV!$A$1:$C$5524,2,0),"") -> 8794 | V70: =IF(U70="",T70,T70/U70) -> 8794 | W70: =IF(V70="","", IFERROR((V70-J70)/J70,"")) -> 0 | Y70: =IFERROR(VLOOKUP(A70,#REF!,3,0),0) -> 0 | Z70: Activo
A71: 70 | C71: Producto | D71: TAU SIN ESTEROIDES X 10 ML. | E71: LABYES | F71: Medicamentos | G71: OJOS | H71: =IF(J71="","",J71/1.21) -> 6546.281 | J71: 7921 | K71: 0.8 | L71: =IF('Global Precios'!J71*(1-I71)*(1+'Global Precios'!K71)>10000,MROUND('Global Precios'!J71*(1-I71)*(1+'Global Precios'!K71),1000),MROUND('Global Precios'!J71*(1-I71)*(1+'Global Precios'!K71),500)) -> 14000 | M71: 10 | N71: ml | P71: 45839 | Q71: =LEN(D71) -> 27 | R71: 30 | T71: =IFERROR(VLOOKUP(D71,BUSCARV!$A$1:$C$5524,2,0),"") -> 7921 | V71: =IF(U71="",T71,T71/U71) -> 7921 | W71: =IF(V71="","", IFERROR((V71-J71)/J71,"")) -> 0 | Y71: =IFERROR(VLOOKUP(A71,#REF!,3,0),0) -> 0 | Z71: Activo
A72: 71 | C72: Producto | D72: BRONCO TOS FORTE X 100 ML | E72: LAMAR | F72: Medicamentos | G72: VITAMINAS Y PROT. HEPATICOS,ETC | H72: =IF(J72="","",J72/1.21) -> 9019.0083 | J72: 10913 | K72: 0.8 | L72: =IF('Global Precios'!J72*(1-I72)*(1+'Global Precios'!K72)>10000,MROUND('Global Precios'!J72*(1-I72)*(1+'Global Precios'!K72),1000),MROUND('Global Precios'!J72*(1-I72)*(1+'Global Precios'!K72),500)) -> 20000 | M72: 100 | N72: ml | P72: 45839 | Q72: =LEN(D72) -> 25 | R72: 30 | T72: =IFERROR(VLOOKUP(D72,BUSCARV!$A$1:$C$5524,2,0),"") -> 10913 | V72: =IF(U72="",T72,T72/U72) -> 10913 | W72: =IF(V72="","", IFERROR((V72-J72)/J72,"")) -> 0 | Y72: =IFERROR(VLOOKUP(A72,#REF!,3,0),0) -> 0 | Z72: Activo
A73: 72 | C73: Producto | D73: CLINDAMICIN 110 MG X BLISTER X 10 COMP | E73: LAMAR | F73: Medicamentos | G73: ANTIBIÓTICOS | H73: =IF(J73="","",J73/1.21) -> 2380.1653 | J73: 2880 | K73: 1 | L73: =IF('Global Precios'!J73*(1-I73)*(1+'Global Precios'!K73)>10000,MROUND('Global Precios'!J73*(1-I73)*(1+'Global Precios'!K73),1000),MROUND('Global Precios'!J73*(1-I73)*(1+'Global Precios'!K73),500)) -> 6000 | M73: 10 | N73: Comprimidos | P73: 45839 | Q73: =LEN(D73) -> 38 | R73: 30 | T73: =IFERROR(VLOOKUP(D73,BUSCARV!$A$1:$C$5524,2,0),"") | V73: =IF(U73="",T73,T73/U73) | W73: =IF(V73="","", IFERROR((V73-J73)/J73,"")) | Y73: =IFERROR(VLOOKUP(A73,#REF!,3,0),0) -> 0 | Z73: Activo
A74: 73 | C74: Producto | D74: DOMINAL MAX PERRO 10-25 KG | E74: KONIG P.A | F74: Medicamentos | G74: PIPETAS | H74: =IF(J74="","",J74/1.21) -> 2386.7769 | J74: 2888 | K74: 0.8 | L74: =IF('Global Precios'!J74*(1-I74)*(1+'Global Precios'!K74)>10000,MROUND('Global Precios'!J74*(1-I74)*(1+'Global Precios'!K74),1000),MROUND('Global Precios'!J74*(1-I74)*(1+'Global Precios'!K74),500)) -> 5000 | P74: 45839 | Q74: =LEN(D74) -> 26 | R74: 30 | T74: =IFERROR(VLOOKUP(D74,BUSCARV!$A$1:$C$5524,2,0),"") -> 2888 | V74: =IF(U74="",T74,T74/U74) -> 2888 | W74: =IF(V74="","", IFERROR((V74-J74)/J74,"")) -> 0 | Y74: =IFERROR(VLOOKUP(A74,#REF!,3,0),0) -> 0 | Z74: Activo
A75: 74 | C75: Producto | D75: DOMINAL MAX PERRO 25-40 KG | E75: KONIG P.A | F75: Medicamentos | G75: PIPETAS | H75: =IF(J75="","",J75/1.21) -> 3222.314 | J75: 3899 | K75: 0.8 | L75: =IF('Global Precios'!J75*(1-I75)*(1+'Global Precios'!K75)>10000,MROUND('Global Precios'!J75*(1-I75)*(1+'Global Precios'!K75),1000),MROUND('Global Precios'!J75*(1-I75)*(1+'Global Precios'!K75),500)) -> 7000 | P75: 45839 | Q75: =LEN(D75) -> 26 | R75: 30 | T75: =IFERROR(VLOOKUP(D75,BUSCARV!$A$1:$C$5524,2,0),"") -> 3899 | V75: =IF(U75="",T75,T75/U75) -> 3899 | W75: =IF(V75="","", IFERROR((V75-J75)/J75,"")) -> 0 | Y75: =IFERROR(VLOOKUP(A75,#REF!,3,0),0) -> 0 | Z75: Activo
A76: 75 | C76: Producto | D76: ENROFLOXACINA 150 MG X BLISTER X 10 COMP (LAMAR) | E76: LAMAR | F76: Medicamentos | G76: ANTIBIÓTICOS | H76: =IF(J76="","",J76/1.21) -> 1611.5702 | J76: 1950 | K76: 1 | L76: =IF('Global Precios'!J76*(1-I76)*(1+'Global Precios'!K76)>10000,MROUND('Global Precios'!J76*(1-I76)*(1+'Global Precios'!K76),1000),MROUND('Global Precios'!J76*(1-I76)*(1+'Global Precios'!K76),500)) -> 4000 | M76: 10 | N76: Comprimidos | P76: 45839 | Q76: =LEN(D76) -> 48 | R76: 30 | T76: =IFERROR(VLOOKUP(D76,BUSCARV!$A$1:$C$5524,2,0),"") | V76: =IF(U76="",T76,T76/U76) | W76: =IF(V76="","", IFERROR((V76-J76)/J76,"")) | Y76: =IFERROR(VLOOKUP(A76,#REF!,3,0),0) -> 0 | Z76: Activo
A77: 76 | C77: Producto | D77: DOMINAL MAX PERRO MAS 40 KG | E77: KONIG P.A | F77: Medicamentos | G77: PIPETAS | H77: =IF(J77="","",J77/1.21) -> 4043.8017 | J77: 4893 | K77: 0.8 | L77: =IF('Global Precios'!J77*(1-I77)*(1+'Global Precios'!K77)>10000,MROUND('Global Precios'!J77*(1-I77)*(1+'Global Precios'!K77),1000),MROUND('Global Precios'!J77*(1-I77)*(1+'Global Precios'!K77),500)) -> 9000 | P77: 45839 | Q77: =LEN(D77) -> 27 | R77: 30 | T77: =IFERROR(VLOOKUP(D77,BUSCARV!$A$1:$C$5524,2,0),"") -> 4893 | V77: =IF(U77="",T77,T77/U77) -> 4893 | W77: =IF(V77="","", IFERROR((V77-J77)/J77,"")) -> 0 | Y77: =IFERROR(VLOOKUP(A77,#REF!,3,0),0) -> 0 | Z77: Activo
A78: 77 | C78: Producto | D78: PERFOS GATO HASTA 4 KG | E78: KUALCOS | F78: Medicamentos | G78: PIPETAS | H78: =IF(J78="","",J78/1.21) -> 919.00826 | J78: 1112 | K78: 0.8 | L78: =IF('Global Precios'!J78*(1-I78)*(1+'Global Precios'!K78)>1000,MROUND('Global Precios'!J78*(1-I78)*(1+'Global Precios'!K78),100),MROUND('Global Precios'!J78*(1-I78)*(1+'Global Precios'!K78),10)) -> 2000 | P78: 45383 | Q78: =LEN(D78) -> 22 | R78: 30 | T78: =IFERROR(VLOOKUP(D78,BUSCARV!$A$1:$C$5524,2,0),"") -> 1312 | V78: =IF(U78="",T78,T78/U78) -> 1312 | W78: =IF(V78="","", IFERROR((V78-J78)/J78,"")) -> 0.17985612 | Y78: =IFERROR(VLOOKUP(A78,#REF!,3,0),0) -> 0 | Z78: Desactivado
A79: 78 | C79: Producto | D79: PERFOS GATO MAS 4 KG | E79: KUALCOS | F79: Medicamentos | G79: PIPETAS | H79: =IF(J79="","",J79/1.21) -> 974.38017 | J79: 1179 | K79: 0.8 | L79: =IF('Global Precios'!J79*(1-I79)*(1+'Global Precios'!K79)>1000,MROUND('Global Precios'!J79*(1-I79)*(1+'Global Precios'!K79),100),MROUND('Global Precios'!J79*(1-I79)*(1+'Global Precios'!K79),10)) -> 2100 | P79: 45383 | Q79: =LEN(D79) -> 20 | R79: 30 | T79: =IFERROR(VLOOKUP(D79,BUSCARV!$A$1:$C$5524,2,0),"") -> 1391 | V79: =IF(U79="",T79,T79/U79) -> 1391 | W79: =IF(V79="","", IFERROR((V79-J79)/J79,"")) -> 0.1798134 | Y79: =IFERROR(VLOOKUP(A79,#REF!,3,0),0) -> 0 | Z79: Desactivado
A80: 79 | C80: Producto | D80: PERFOS MAX CANINOS 10-20 KG | E80: KUALCOS | F80: Medicamentos | G80: PIPETAS | H80: =IF(J80="","",J80/1.21) -> 1306.6116 | J80: 1581 | K80: 0.8 | L80: =IF('Global Precios'!J80*(1-I80)*(1+'Global Precios'!K80)>1000,MROUND('Global Precios'!J80*(1-I80)*(1+'Global Precios'!K80),100),MROUND('Global Precios'!J80*(1-I80)*(1+'Global Precios'!K80),10)) -> 2800 | P80: 45383 | Q80: =LEN(D80) -> 27 | R80: 30 | T80: =IFERROR(VLOOKUP(D80,BUSCARV!$A$1:$C$5524,2,0),"") -> 1866 | V80: =IF(U80="",T80,T80/U80) -> 1866 | W80: =IF(V80="","", IFERROR((V80-J80)/J80,"")) -> 0.18026565 | Y80: =IFERROR(VLOOKUP(A80,#REF!,3,0),0) -> 0 | Z80: Desactivado
A81: 80 | C81: Producto | D81: PERFOS MAX CANINOS 20-40 KG | E81: KUALCOS | F81: Medicamentos | G81: PIPETAS | H81: =IF(J81="","",J81/1.21) -> 1466.1157 | J81: 1774 | K81: 0.8 | L81: =IF('Global Precios'!J81*(1-I81)*(1+'Global Precios'!K81)>1000,MROUND('Global Precios'!J81*(1-I81)*(1+'Global Precios'!K81),100),MROUND('Global Precios'!J81*(1-I81)*(1+'Global Precios'!K81),10)) -> 3200 | P81: 45383 | Q81: =LEN(D81) -> 27 | R81: 30 | T81: =IFERROR(VLOOKUP(D81,BUSCARV!$A$1:$C$5524,2,0),"") -> 2093 | V81: =IF(U81="",T81,T81/U81) -> 2093 | W81: =IF(V81="","", IFERROR((V81-J81)/J81,"")) -> 0.17981962 | Y81: =IFERROR(VLOOKUP(A81,#REF!,3,0),0) -> 0 | Z81: Desactivado
A82: 81 | C82: Producto | D82: PERFOS MAX CANINOS 5-10 KG | E82: KUALCOS | F82: Medicamentos | G82: PIPETAS | H82: =IF(J82="","",J82/1.21) -> 1155.3719 | J82: 1398 | K82: 0.8 | L82: =IF('Global Precios'!J82*(1-I82)*(1+'Global Precios'!K82)>1000,MROUND('Global Precios'!J82*(1-I82)*(1+'Global Precios'!K82),100),MROUND('Global Precios'!J82*(1-I82)*(1+'Global Precios'!K82),10)) -> 2500 | P82: 45383 | Q82: =LEN(D82) -> 26 | R82: 30 | T82: =IFERROR(VLOOKUP(D82,BUSCARV!$A$1:$C$5524,2,0),"") -> 1649 | V82: =IF(U82="",T82,T82/U82) -> 1649 | W82: =IF(V82="","", IFERROR((V82-J82)/J82,"")) -> 0.1795422 | Y82: =IFERROR(VLOOKUP(A82,#REF!,3,0),0) -> 0 | Z82: Desactivado
A83: 82 | C83: Producto | D83: ENTEROSULFATRIN SUSP X 100 ML | E83: LAMAR | F83: Medicamentos | G83: ANTIBIÓTICOS | H83: =IF(J83="","",J83/1.21) -> 3399.1736 | J83: 4113 | K83: 1 | L83: =IF('Global Precios'!J83*(1-I83)*(1+'Global Precios'!K83)>10000,MROUND('Global Precios'!J83*(1-I83)*(1+'Global Precios'!K83),1000),MROUND('Global Precios'!J83*(1-I83)*(1+'Global Precios'!K83),500)) -> 8000 | M83: 100 | N83: ML | P83: 45839 | Q83: =LEN(D83) -> 29 | R83: 30 | T83: =IFERROR(VLOOKUP(D83,BUSCARV!$A$1:$C$5524,2,0),"") -> 4113 | V83: =IF(U83="",T83,T83/U83) -> 4113 | W83: =IF(V83="","", IFERROR((V83-J83)/J83,"")) -> 0 | Y83: =IFERROR(VLOOKUP(A83,#REF!,3,0),0) -> 0 | Z83: Activo
A84: 83 | C84: Producto | D84: METOCLOPRAMIDA GOTAS X 15 ML | E84: LAMAR | F84: Medicamentos | G84: VITAMINAS Y PROT. HEPATICOS,ETC | H84: =IF(J84="","",J84/1.21) -> 4148.7603 | J84: 5020 | K84: 0.8 | L84: =IF('Global Precios'!J84*(1-I84)*(1+'Global Precios'!K84)>10000,MROUND('Global Precios'!J84*(1-I84)*(1+'Global Precios'!K84),1000),MROUND('Global Precios'!J84*(1-I84)*(1+'Global Precios'!K84),500)) -> 9000 | M84: 15 | N84: ml | P84: 45839 | Q84: =LEN(D84) -> 28 | R84: 30 | T84: =IFERROR(VLOOKUP(D84,BUSCARV!$A$1:$C$5524,2,0),"") -> 5020 | V84: =IF(U84="",T84,T84/U84) -> 5020 | W84: =IF(V84="","", IFERROR((V84-J84)/J84,"")) -> 0 | Y84: =IFERROR(VLOOKUP(A84,#REF!,3,0),0) -> 0 | Z84: Activo
A85: 84 | C85: Producto | D85: MOXIDEX PLUS HOSPITALARIO X 1 COMPRIMIDO | E85: MAYORS | F85: Medicamentos | G85: ANTIPARASITARIOS INTERNOS | H85: =IF(J85="","",J85/1.21) -> 702.47934 | J85: 850 | K85: 0.8 | L85: =IF('Global Precios'!J85*(1-I85)*(1+'Global Precios'!K85)>10000,MROUND('Global Precios'!J85*(1-I85)*(1+'Global Precios'!K85),1000),MROUND('Global Precios'!J85*(1-I85)*(1+'Global Precios'!K85),500)) -> 1500 | M85: 1 | N85: Comprimidos | P85: 45839 | Q85: =LEN(D85) -> 40 | R85: 30 | T85: =IFERROR(VLOOKUP(D85,BUSCARV!$A$1:$C$5524,2,0),"") | V85: =IF(U85="",T85,T85/U85) | W85: =IF(V85="","", IFERROR((V85-J85)/J85,"")) | Y85: =IFERROR(VLOOKUP(A85,#REF!,3,0),0) -> 0 | Z85: Activo
A86: 85 | C86: Producto | D86: TOLTRAZOL "PLUS" SUSPENSION X 10 ML | E86: MAYORS | F86: Medicamentos | G86: ANTIPARASITARIOS INTERNOS | H86: =IF(J86="","",J86/1.21) -> 6446.281 | J86: 7800 | K86: 1 | L86: =IF('Global Precios'!J86*(1-I86)*(1+'Global Precios'!K86)>10000,MROUND('Global Precios'!J86*(1-I86)*(1+'Global Precios'!K86),1000),MROUND('Global Precios'!J86*(1-I86)*(1+'Global Precios'!K86),500)) -> 16000 | M86: 10 | N86: ml | P86: 45839 | Q86: =LEN(D86) -> 35 | R86: 30 | T86: =IFERROR(VLOOKUP(D86,BUSCARV!$A$1:$C$5524,2,0),"") | V86: =IF(U86="",T86,T86/U86) | W86: =IF(V86="","", IFERROR((V86-J86)/J86,"")) | Y86: =IFERROR(VLOOKUP(A86,#REF!,3,0),0) -> 0 | Z86: Activo
A87: 86 | C87: Producto | D87: SHAMPOO AMITRAZ AL 0.25% X 250 ML | E87: OSSPRET | F87: Medicamentos | G87: LIQUIDOS Y SHAMPOOS | H87: =IF(J87="","",J87/1.21) -> 4705.7851 | J87: 5694 | K87: 0.8 | L87: =IF('Global Precios'!J87*(1-I87)*(1+'Global Precios'!K87)>10000,MROUND('Global Precios'!J87*(1-I87)*(1+'Global Precios'!K87),1000),MROUND('Global Precios'!J87*(1-I87)*(1+'Global Precios'!K87),500)) -> 10000 | M87: 250 | N87: ml | P87: 45839 | Q87: =LEN(D87) -> 33 | R87: 30 | T87: =IFERROR(VLOOKUP(D87,BUSCARV!$A$1:$C$5524,2,0),"") -> 5694 | V87: =IF(U87="",T87,T87/U87) -> 5694 | W87: =IF(V87="","", IFERROR((V87-J87)/J87,"")) -> 0 | Y87: =IFERROR(VLOOKUP(A87,#REF!,3,0),0) -> 0 | Z87: Activo
A88: 87 | C88: Producto | D88: SHAMPOO CLOREXPRO X 250 ML | E88: OSSPRET | F88: Medicamentos | G88: LIQUIDOS Y SHAMPOOS | H88: =IF(J88="","",J88/1.21) -> 5064.4628 | J88: 6128 | K88: 0.8 | L88: =IF('Global Precios'!J88*(1-I88)*(1+'Global Precios'!K88)>10000,MROUND('Global Precios'!J88*(1-I88)*(1+'Global Precios'!K88),1000),MROUND('Global Precios'!J88*(1-I88)*(1+'Global Precios'!K88),500)) -> 11000 | M88: 250 | N88: ml | P88: 45839 | Q88: =LEN(D88) -> 26 | R88: 30 | T88: =IFERROR(VLOOKUP(D88,BUSCARV!$A$1:$C$5524,2,0),"") -> 6128 | V88: =IF(U88="",T88,T88/U88) -> 6128 | W88: =IF(V88="","", IFERROR((V88-J88)/J88,"")) -> 0 | Y88: =IFERROR(VLOOKUP(A88,#REF!,3,0),0) -> 0 | Z88: Activo
A89: 88 | C89: Producto | D89: SHAMPOO MEDICADO HIPOALERGENICO X 250 ML | E89: OSSPRET | F89: Medicamentos | G89: LIQUIDOS Y SHAMPOOS | H89: =IF(J89="","",J89/1.21) -> 2650.4132 | J89: 3207 | K89: 0.8 | L89: =IF('Global Precios'!J89*(1-I89)*(1+'Global Precios'!K89)>1000,MROUND('Global Precios'!J89*(1-I89)*(1+'Global Precios'!K89),100),MROUND('Global Precios'!J89*(1-I89)*(1+'Global Precios'!K89),10)) -> 5800 | M89: 250 | N89: ml | P89: 45383 | Q89: =LEN(D89) -> 40 | R89: 30 | T89: =IFERROR(VLOOKUP(D89,BUSCARV!$A$1:$C$5524,2,0),"") -> 4932 | V89: =IF(U89="",T89,T89/U89) -> 4932 | W89: =IF(V89="","", IFERROR((V89-J89)/J89,"")) -> 0.53788587 | Y89: =IFERROR(VLOOKUP(A89,#REF!,3,0),0) -> 0 | Z89: Desactivado
A90: 89 | C90: Producto | D90: SHAMPOO PARA CACHORROS X 250 ML | E90: OSSPRET | F90: Medicamentos | G90: LIQUIDOS Y SHAMPOOS | H90: =IF(J90="","",J90/1.21) -> 4271.9008 | J90: 5169 | K90: 0.8 | L90: =IF('Global Precios'!J90*(1-I90)*(1+'Global Precios'!K90)>10000,MROUND('Global Precios'!J90*(1-I90)*(1+'Global Precios'!K90),1000),MROUND('Global Precios'!J90*(1-I90)*(1+'Global Precios'!K90),500)) -> 9500 | M90: 250 | N90: ml | P90: 45839 | Q90: =LEN(D90) -> 31 | R90: 30 | T90: =IFERROR(VLOOKUP(D90,BUSCARV!$A$1:$C$5524,2,0),"") -> 5169 | V90: =IF(U90="",T90,T90/U90) -> 5169 | W90: =IF(V90="","", IFERROR((V90-J90)/J90,"")) -> 0 | Y90: =IFERROR(VLOOKUP(A90,#REF!,3,0),0) -> 0 | Z90: Activo
A91: 90 | C91: Producto | D91: SHAMPOO PERFUMADO MIX FRUTAL X 250 ML | E91: OSSPRET | F91: Medicamentos | G91: LIQUIDOS Y SHAMPOOS | H91: =IF(J91="","",J91/1.21) -> 3717.3554 | J91: 4498 | K91: 0.8 | L91: =IF('Global Precios'!J91*(1-I91)*(1+'Global Precios'!K91)>10000,MROUND('Global Precios'!J91*(1-I91)*(1+'Global Precios'!K91),1000),MROUND('Global Precios'!J91*(1-I91)*(1+'Global Precios'!K91),500)) -> 8000 | P91: 45839 | Q91: =LEN(D91) -> 37 | R91: 30 | T91: =IFERROR(VLOOKUP(D91,BUSCARV!$A$1:$C$5524,2,0),"") -> 5169 | V91: =IF(U91="",T91,T91/U91) -> 5169 | W91: =IF(V91="","", IFERROR((V91-J91)/J91,"")) -> 0.14917741 | Y91: =IFERROR(VLOOKUP(A91,#REF!,3,0),0) -> 0 | Z91: Desactivado
A92: 91 | C92: Producto | D92: SIMPARICA 10 MG (2,5 A 5 KG) | E92: ZOETIS P.A | F92: Medicamentos | G92: PASTILLAS PULGAS,GARRAPATAS,ACAROS | H92: =IF(J92="","",J92/1.21) -> 8557.0248 | J92: 10354 | K92: 0.8 | L92: =IF('Global Precios'!J92*(1-I92)*(1+'Global Precios'!K92)>10000,MROUND('Global Precios'!J92*(1-I92)*(1+'Global Precios'!K92),1000),MROUND('Global Precios'!J92*(1-I92)*(1+'Global Precios'!K92),500)) -> 19000 | M92: 10 | N92: mg | P92: 45839 | Q92: =LEN(D92) -> 28 | R92: 30 | T92: =IFERROR(VLOOKUP(D92,BUSCARV!$A$1:$C$5524,2,0),"") -> 8734 | V92: =IF(U92="",T92,T92/U92) -> 8734 | W92: =IF(V92="","", IFERROR((V92-J92)/J92,"")) -> -0.15646127 | Y92: =IFERROR(VLOOKUP(A92,#REF!,3,0),0) -> 0 | Z92: Activo
A93: 92 | C93: Producto | D93: SIMPARICA 20 MG (5 A 10 KG) | E93: ZOETIS P.A | F93: Medicamentos | G93: PASTILLAS PULGAS,GARRAPATAS,ACAROS | H93: =IF(J93="","",J93/1.21) -> 8729.7521 | J93: 10563 | K93: 0.8 | L93: =IF('Global Precios'!J93*(1-I93)*(1+'Global Precios'!K93)>10000,MROUND('Global Precios'!J93*(1-I93)*(1+'Global Precios'!K93),1000),MROUND('Global Precios'!J93*(1-I93)*(1+'Global Precios'!K93),500)) -> 19000 | M93: 20 | N93: mg | P93: 45839 | Q93: =LEN(D93) -> 27 | R93: 30 | T93: =IFERROR(VLOOKUP(D93,BUSCARV!$A$1:$C$5524,2,0),"") -> 8899 | V93: =IF(U93="",T93,T93/U93) -> 8899 | W93: =IF(V93="","", IFERROR((V93-J93)/J93,"")) -> -0.157531 | Y93: =IFERROR(VLOOKUP(A93,#REF!,3,0),0) -> 0 | Z93: Activo
A94: 93 | C94: Producto | D94: SIMPARICA 40 MG (10 A 20 KG) | E94: ZOETIS P.A | F94: Medicamentos | G94: PASTILLAS PULGAS,GARRAPATAS,ACAROS | H94: =IF(J94="","",J94/1.21) -> 11314.05 | J94: 13690 | K94: 0.8 | L94: =IF('Global Precios'!J94*(1-I94)*(1+'Global Precios'!K94)>10000,MROUND('Global Precios'!J94*(1-I94)*(1+'Global Precios'!K94),1000),MROUND('Global Precios'!J94*(1-I94)*(1+'Global Precios'!K94),500)) -> 25000 | M94: 40 | N94: mg | P94: 45839 | Q94: =LEN(D94) -> 28 | R94: 30 | T94: =IFERROR(VLOOKUP(D94,BUSCARV!$A$1:$C$5524,2,0),"") -> 11536 | V94: =IF(U94="",T94,T94/U94) -> 11536 | W94: =IF(V94="","", IFERROR((V94-J94)/J94,"")) -> -0.15734112 | Y94: =IFERROR(VLOOKUP(A94,#REF!,3,0),0) -> 0 | Z94: Activo
A95: 94 | C95: Producto | D95: SIMPARICA 80 MG (20 A 40 KG) | E95: ZOETIS P.A | F95: Medicamentos | G95: PASTILLAS PULGAS,GARRAPATAS,ACAROS | H95: =IF(J95="","",J95/1.21) -> 13254.545 | J95: 16038 | K95: 0.8 | L95: =IF('Global Precios'!J95*(1-I95)*(1+'Global Precios'!K95)>10000,MROUND('Global Precios'!J95*(1-I95)*(1+'Global Precios'!K95),1000),MROUND('Global Precios'!J95*(1-I95)*(1+'Global Precios'!K95),500)) -> 29000 | M95: 80 | N95: mg | P95: 45839 | Q95: =LEN(D95) -> 28 | R95: 30 | T95: =IFERROR(VLOOKUP(D95,BUSCARV!$A$1:$C$5524,2,0),"") -> 13513 | V95: =IF(U95="",T95,T95/U95) -> 13513 | W95: =IF(V95="","", IFERROR((V95-J95)/J95,"")) -> -0.15743858 | Y95: =IFERROR(VLOOKUP(A95,#REF!,3,0),0) -> 0 | Z95: Activo
A96: 95 | C96: Producto | D96: PETS PROTECTOR SPRAY X 100 ML | E96: ZOOVET P.A | F96: Medicamentos | G96: LIQUIDOS Y SHAMPOOS | H96: =IF(J96="","",J96/1.21) -> 9318.1818 | J96: 11275 | K96: 0.8 | L96: =IF('Global Precios'!J96*(1-I96)*(1+'Global Precios'!K96)>10000,MROUND('Global Precios'!J96*(1-I96)*(1+'Global Precios'!K96),1000),MROUND('Global Precios'!J96*(1-I96)*(1+'Global Precios'!K96),500)) -> 20000 | M96: 100 | N96: ml | P96: 45839 | Q96: =LEN(D96) -> 29 | R96: 30 | T96: =IFERROR(VLOOKUP(D96,BUSCARV!$A$1:$C$5524,2,0),"") -> 11275 | V96: =IF(U96="",T96,T96/U96) -> 11275 | W96: =IF(V96="","", IFERROR((V96-J96)/J96,"")) -> 0 | Y96: =IFERROR(VLOOKUP(A96,#REF!,3,0),0) -> 0 | Z96: Activo
A97: 96 | C97: Producto | D97: QUANTUM DA2 PPVL X DS | E97: MSD P.A | F97: Medicamentos | H97: =IF(J97="","",J97/1.21) -> 4987.6033 | J97: 6035 | L97: =IF('Global Precios'!J97*(1-I97)*(1+'Global Precios'!K97)>1000,MROUND('Global Precios'!J97*(1-I97)*(1+'Global Precios'!K97),100),MROUND('Global Precios'!J97*(1-I97)*(1+'Global Precios'!K97),10)) -> 6000 | P97: 45413 | Q97: =LEN(D97) -> 21 | R97: 30 | T97: =IFERROR(VLOOKUP(D97,BUSCARV!$A$1:$C$5524,2,0),"") -> 7703 | V97: =IF(U97="",T97,T97/U97) -> 7703 | W97: =IF(V97="","", IFERROR((V97-J97)/J97,"")) -> 0.27638774 | Y97: =IFERROR(VLOOKUP(A97,#REF!,3,0),0) -> 0 | Z97: Desactivado
A98: 97 | C98: Producto | D98: APTO X 160 COMP | F98: Medicamentos | G98: ANTIPARASITARIOS INTERNOS | H98: =IF(J98="","",J98/1.21) -> 0 | J98: 0 | K98: 1 | L98: =IF('Global Precios'!J98*(1-I98)*(1+'Global Precios'!K98)>10000,MROUND('Global Precios'!J98*(1-I98)*(1+'Global Precios'!K98),1000),MROUND('Global Precios'!J98*(1-I98)*(1+'Global Precios'!K98),500)) -> 0 | P98: 44866 | Q98: =LEN(D98) -> 15 | R98: 0 | T98: =IFERROR(VLOOKUP(D98,BUSCARV!$A$1:$C$5524,2,0),"") -> 44385 | V98: =IF(U98="",T98,T98/U98) -> 44385 | W98: =IF(V98="","", IFERROR((V98-J98)/J98,"")) | Y98: =IFERROR(VLOOKUP(A98,#REF!,3,0),0) -> 0 | Z98: Activo
A99: 98 | H99: =IF(J99="","",J99/1.21) -> 0 | J99: 0 | K99: 1 | L99: =IF('Global Precios'!J99*(1-I99)*(1+'Global Precios'!K99)>10000,MROUND('Global Precios'!J99*(1-I99)*(1+'Global Precios'!K99),1000),MROUND('Global Precios'!J99*(1-I99)*(1+'Global Precios'!K99),500)) -> 0 | P99: 44598 | Q99: =LEN(D99) -> 0 | R99: 0 | T99: =IFERROR(VLOOKUP(D99,BUSCARV!$A$1:$C$5524,2,0),"") | V99: =IF(U99="",T99,T99/U99) | W99: =IF(V99="","", IFERROR((V99-J99)/J99,"")) | Y99: =IFERROR(VLOOKUP(A99,#REF!,3,0),0) -> 0 | Z99: Activo
A100: 99 | C100: Producto | D100: FELINE FULLSPOT 02-05 KG | F100: Medicamentos | G100: ANTIPARASITARIOS INTERNOS | H100: =IF(J100="","",J100/1.21) -> 11735.537 | J100: 14200 | K100: 0.8 | L100: =IF('Global Precios'!J100*(1-I100)*(1+'Global Precios'!K100)>10000,MROUND('Global Precios'!J100*(1-I100)*(1+'Global Precios'!K100),1000),MROUND('Global Precios'!J100*(1-I100)*(1+'Global Precios'!K100),500)) -> 26000 | M100: 1 | N100: Unidad | P100: 46023 | Q100: =LEN(D100) -> 24 | R100: 30 | T100: =IFERROR(VLOOKUP(D100,BUSCARV!$A$1:$C$5524,2,0),"") -> 12822 | V100: =IF(U100="",T100,T100/U100) -> 12822 | W100: =IF(V100="","", IFERROR((V100-J100)/J100,"")) -> -0.097042254 | Y100: =IFERROR(VLOOKUP(A100,#REF!,3,0),0) -> 0 | Z100: Activo
...

Sheet ADMGlobal
A1: =IF(E1="","", IF('Global Precios'!B2="",0,'Global Precios'!B2)) -> 0 | B1: =IF('Global Precios'!B2="","",'Global Precios'!B2) | C1: =IF('Global Precios'!A2="","",'Global Precios'!A2) -> 1 | E1: =IF('Global Precios'!D2="","",'Global Precios'!D2) -> Castración Gata | G1: =IFERROR(VLOOKUP(C1,'BuscarV Stock'!$A$2:$C$478,3,0),"AAA") -> 0 | H1: =IF(E1="","",0.21) -> 0.21 | I1: =IF('Global Precios'!H2="","",'Global Precios'!H2) -> 68163.636 | J1: =IF('Global Precios'!K2="","",'Global Precios'!K2) | K1: =IF('Global Precios'!Z2="Desactivado",0,IF('Global Precios'!L2="","",'Global Precios'!L2)) -> 82000 | R1: =IF('Global Precios'!F2="","",'Global Precios'!F2) -> Clinica | T1: =IF('Global Precios'!E2="","",'Global Precios'!E2) -> Arlekyn | V1: =IF(K1="","",0) -> 0 | AB1: =IF(K1="","",1) -> 1 | AC1: =IF(K1="","",1) -> 1 | AD1: =IF(K1="","",1) -> 1 | AE1: =AD1 -> 1
A2: =IF(E2="","", IF('Global Precios'!B3="",0,'Global Precios'!B3)) -> 0 | B2: =IF('Global Precios'!B3="","",'Global Precios'!B3) | C2: =IF('Global Precios'!A3="","",'Global Precios'!A3) -> 2 | E2: =IF('Global Precios'!D3="","",'Global Precios'!D3) -> Castración perra hasta 10 kg | G2: =IFERROR(VLOOKUP(C2,'BuscarV Stock'!$A$2:$C$478,3,0),"AAA") -> 0 | H2: =IF(E2="","",0.21) -> 0.21 | I2: =IF('Global Precios'!H3="","",'Global Precios'!H3) -> 83251.24 | J2: =IF('Global Precios'!K3="","",'Global Precios'!K3) | K2: =IF('Global Precios'!Z3="Desactivado",0,IF('Global Precios'!L3="","",'Global Precios'!L3)) -> 101000 | R2: =IF('Global Precios'!F3="","",'Global Precios'!F3) -> Clinica | T2: =IF('Global Precios'!E3="","",'Global Precios'!E3) -> Arlekyn | V2: =IF(K2="","",0) -> 0 | AB2: =IF(K2="","",1) -> 1 | AC2: =IF(K2="","",1) -> 1 | AD2: =IF(K2="","",1) -> 1 | AE2: =AD2 -> 1
A3: =IF(E3="","", IF('Global Precios'!B4="",0,'Global Precios'!B4)) -> 0 | B3: =IF('Global Precios'!B4="","",'Global Precios'!B4) | C3: =IF('Global Precios'!A4="","",'Global Precios'!A4) -> 3 | E3: =IF('Global Precios'!D4="","",'Global Precios'!D4) -> Castración perra hasta 20 kg | G3: =IFERROR(VLOOKUP(C3,'BuscarV Stock'!$A$2:$C$478,3,0),"AAA") -> 0 | H3: =IF(E3="","",0.21) -> 0.21 | I3: =IF('Global Precios'!H4="","",'Global Precios'!H4) -> 85819.835 | J3: =IF('Global Precios'!K4="","",'Global Precios'!K4) | K3: =IF('Global Precios'!Z4="Desactivado",0,IF('Global Precios'!L4="","",'Global Precios'!L4)) -> 104000 | R3: =IF('Global Precios'!F4="","",'Global Precios'!F4) -> Clinica | T3: =IF('Global Precios'!E4="","",'Global Precios'!E4) -> Arlekyn | V3: =IF(K3="","",0) -> 0 | AB3: =IF(K3="","",1) -> 1 | AC3: =IF(K3="","",1) -> 1 | AD3: =IF(K3="","",1) -> 1 | AE3: =AD3 -> 1
A4: =IF(E4="","", IF('Global Precios'!B5="",0,'Global Precios'!B5)) -> 0 | B4: =IF('Global Precios'!B5="","",'Global Precios'!B5) | C4: =IF('Global Precios'!A5="","",'Global Precios'!A5) -> 4 | E4: =IF('Global Precios'!D5="","",'Global Precios'!D5) -> Castración perra hasta 30 kg | G4: =IFERROR(VLOOKUP(C4,'BuscarV Stock'!$A$2:$C$478,3,0),"AAA") -> 0 | H4: =IF(E4="","",0.21) -> 0.21 | I4: =IF('Global Precios'!H5="","",'Global Precios'!H5) -> 90454.545 | J4: =IF('Global Precios'!K5="","",'Global Precios'!K5) | K4: =IF('Global Precios'!Z5="Desactivado",0,IF('Global Precios'!L5="","",'Global Precios'!L5)) -> 109000 | R4: =IF('Global Precios'!F5="","",'Global Precios'!F5) -> Clinica | T4: =IF('Global Precios'!E5="","",'Global Precios'!E5) -> Arlekyn | V4: =IF(K4="","",0) -> 0 | AB4: =IF(K4="","",1) -> 1 | AC4: =IF(K4="","",1) -> 1 | AD4: =IF(K4="","",1) -> 1 | AE4: =AD4 -> 1
A5: =IF(E5="","", IF('Global Precios'!B6="",0,'Global Precios'!B6)) -> 0 | B5: =IF('Global Precios'!B6="","",'Global Precios'!B6) | C5: =IF('Global Precios'!A6="","",'Global Precios'!A6) -> 5 | E5: =IF('Global Precios'!D6="","",'Global Precios'!D6) -> Castración perra hasta 40 kg | G5: =IFERROR(VLOOKUP(C5,'BuscarV Stock'!$A$2:$C$478,3,0),"AAA") -> 0 | H5: =IF(E5="","",0.21) -> 0.21 | I5: =IF('Global Precios'!H6="","",'Global Precios'!H6) -> 97890.083 | J5: =IF('Global Precios'!K6="","",'Global Precios'!K6) | K5: =IF('Global Precios'!Z6="Desactivado",0,IF('Global Precios'!L6="","",'Global Precios'!L6)) -> 118000 | R5: =IF('Global Precios'!F6="","",'Global Precios'!F6) -> Clinica | T5: =IF('Global Precios'!E6="","",'Global Precios'!E6) -> Arlekyn | V5: =IF(K5="","",0) -> 0 | AB5: =IF(K5="","",1) -> 1 | AC5: =IF(K5="","",1) -> 1 | AD5: =IF(K5="","",1) -> 1 | AE5: =AD5 -> 1
A6: =IF(E6="","", IF('Global Precios'!B7="",0,'Global Precios'!B7)) -> 0 | B6: =IF('Global Precios'!B7="","",'Global Precios'!B7) | C6: =IF('Global Precios'!A7="","",'Global Precios'!A7) -> 6 | E6: =IF('Global Precios'!D7="","",'Global Precios'!D7) -> Castración perra hasta 50 kg | G6: =IFERROR(VLOOKUP(C6,'BuscarV Stock'!$A$2:$C$478,3,0),"AAA") -> 0 | H6: =IF(E6="","",0.21) -> 0.21 | I6: =IF('Global Precios'!H7="","",'Global Precios'!H7) -> 105325.62 | J6: =IF('Global Precios'!K7="","",'Global Precios'!K7) | K6: =IF('Global Precios'!Z7="Desactivado",0,IF('Global Precios'!L7="","",'Global Precios'!L7)) -> 127000 | R6: =IF('Global Precios'!F7="","",'Global Precios'!F7) -> Clinica | T6: =IF('Global Precios'!E7="","",'Global Precios'!E7) -> Arlekyn | V6: =IF(K6="","",0) -> 0 | AB6: =IF(K6="","",1) -> 1 | AC6: =IF(K6="","",1) -> 1 | AD6: =IF(K6="","",1) -> 1 | AE6: =AD6 -> 1
A7: =IF(E7="","", IF('Global Precios'!B8="",0,'Global Precios'!B8)) -> 0 | B7: =IF('Global Precios'!B8="","",'Global Precios'!B8) | C7: =IF('Global Precios'!A8="","",'Global Precios'!A8) -> 7 | E7: =IF('Global Precios'!D8="","",'Global Precios'!D8) -> Castración perra hasta 60 kg | G7: =IFERROR(VLOOKUP(C7,'BuscarV Stock'!$A$2:$C$478,3,0),"AAA") -> 0 | H7: =IF(E7="","",0.21) -> 0.21 | I7: =IF('Global Precios'!H8="","",'Global Precios'!H8) -> 114000.83 | J7: =IF('Global Precios'!K8="","",'Global Precios'!K8) | K7: =IF('Global Precios'!Z8="Desactivado",0,IF('Global Precios'!L8="","",'Global Precios'!L8)) -> 138000 | R7: =IF('Global Precios'!F8="","",'Global Precios'!F8) -> Clinica | T7: =IF('Global Precios'!E8="","",'Global Precios'!E8) -> Arlekyn | V7: =IF(K7="","",0) -> 0 | AB7: =IF(K7="","",1) -> 1 | AC7: =IF(K7="","",1) -> 1 | AD7: =IF(K7="","",1) -> 1 | AE7: =AD7 -> 1
A8: =IF(E8="","", IF('Global Precios'!B9="",0,'Global Precios'!B9)) -> 0 | B8: =IF('Global Precios'!B9="","",'Global Precios'!B9) | C8: =IF('Global Precios'!A9="","",'Global Precios'!A9) -> 8 | E8: =IF('Global Precios'!D9="","",'Global Precios'!D9) -> Corte de colitas camadas hasta 3 cachorros | G8: =IFERROR(VLOOKUP(C8,'BuscarV Stock'!$A$2:$C$478,3,0),"AAA") -> 0 | H8: =IF(E8="","",0.21) -> 0.21 | I8: =IF('Global Precios'!H9="","",'Global Precios'!H9) -> 14871.074 | J8: =IF('Global Precios'!K9="","",'Global Precios'!K9) | K8: =IF('Global Precios'!Z9="Desactivado",0,IF('Global Precios'!L9="","",'Global Precios'!L9)) -> 0 | R8: =IF('Global Precios'!F9="","",'Global Precios'!F9) -> Clinica | T8: =IF('Global Precios'!E9="","",'Global Precios'!E9) -> Arlekyn | V8: =IF(K8="","",0) -> 0 | AB8: =IF(K8="","",1) -> 1 | AC8: =IF(K8="","",1) -> 1 | AD8: =IF(K8="","",1) -> 1 | AE8: =AD8 -> 1
A9: =IF(E9="","", IF('Global Precios'!B10="",0,'Global Precios'!B10)) -> 0 | B9: =IF('Global Precios'!B10="","",'Global Precios'!B10) | C9: =IF('Global Precios'!A10="","",'Global Precios'!A10) -> 9 | E9: =IF('Global Precios'!D10="","",'Global Precios'!D10) -> Corte de colitas camadas hasta 4 cachorros | G9: =IFERROR(VLOOKUP(C9,'BuscarV Stock'!$A$2:$C$478,3,0),"AAA") -> 0 | H9: =IF(E9="","",0.21) -> 0.21 | I9: =IF('Global Precios'!H10="","",'Global Precios'!H10) -> 12143.802 | J9: =IF('Global Precios'!K10="","",'Global Precios'!K10) | K9: =IF('Global Precios'!Z10="Desactivado",0,IF('Global Precios'!L10="","",'Global Precios'!L10)) -> 0 | R9: =IF('Global Precios'!F10="","",'Global Precios'!F10) -> Clinica | T9: =IF('Global Precios'!E10="","",'Global Precios'!E10) -> Arlekyn | V9: =IF(K9="","",0) -> 0 | AB9: =IF(K9="","",1) -> 1 | AC9: =IF(K9="","",1) -> 1 | AD9: =IF(K9="","",1) -> 1 | AE9: =AD9 -> 1
A10: =IF(E10="","", IF('Global Precios'!B11="",0,'Global Precios'!B11)) -> 0 | B10: =IF('Global Precios'!B11="","",'Global Precios'!B11) | C10: =IF('Global Precios'!A11="","",'Global Precios'!A11) -> 10 | E10: =IF('Global Precios'!D11="","",'Global Precios'!D11) -> Eutanasia hasta 10 kg | G10: =IFERROR(VLOOKUP(C10,'BuscarV Stock'!$A$2:$C$478,3,0),"AAA") -> 0 | H10: =IF(E10="","",0.21) -> 0.21 | I10: =IF('Global Precios'!H11="","",'Global Precios'!H11) -> 50544.628 | J10: =IF('Global Precios'!K11="","",'Global Precios'!K11) | K10: =IF('Global Precios'!Z11="Desactivado",0,IF('Global Precios'!L11="","",'Global Precios'!L11)) -> 61000 | R10: =IF('Global Precios'!F11="","",'Global Precios'!F11) -> Clinica | T10: =IF('Global Precios'!E11="","",'Global Precios'!E11) -> Arlekyn | V10: =IF(K10="","",0) -> 0 | AB10: =IF(K10="","",1) -> 1 | AC10: =IF(K10="","",1) -> 1 | AD10: =IF(K10="","",1) -> 1 | AE10: =AD10 -> 1
A11: =IF(E11="","", IF('Global Precios'!B12="",0,'Global Precios'!B12)) -> 0 | B11: =IF('Global Precios'!B12="","",'Global Precios'!B12) | C11: =IF('Global Precios'!A12="","",'Global Precios'!A12) -> 11 | E11: =IF('Global Precios'!D12="","",'Global Precios'!D12) -> Eutanasia hasta 20 kg | G11: =IFERROR(VLOOKUP(C11,'BuscarV Stock'!$A$2:$C$478,3,0),"AAA") -> 0 | H11: =IF(E11="","",0.21) -> 0.21 | I11: =IF('Global Precios'!H12="","",'Global Precios'!H12) -> 60022.314 | J11: =IF('Global Precios'!K12="","",'Global Precios'!K12) | K11: =IF('Global Precios'!Z12="Desactivado",0,IF('Global Precios'!L12="","",'Global Precios'!L12)) -> 73000 | R11: =IF('Global Precios'!F12="","",'Global Precios'!F12) -> Clinica | T11: =IF('Global Precios'!E12="","",'Global Precios'!E12) -> Arlekyn | V11: =IF(K11="","",0) -> 0 | AB11: =IF(K11="","",1) -> 1 | AC11: =IF(K11="","",1) -> 1 | AD11: =IF(K11="","",1) -> 1 | AE11: =AD11 -> 1
A12: =IF(E12="","", IF('Global Precios'!B13="",0,'Global Precios'!B13)) -> 0 | B12: =IF('Global Precios'!B13="","",'Global Precios'!B13) | C12: =IF('Global Precios'!A13="","",'Global Precios'!A13) -> 12 | E12: =IF('Global Precios'!D13="","",'Global Precios'!D13) -> Eutanasia hasta 30 kg | G12: =IFERROR(VLOOKUP(C12,'BuscarV Stock'!$A$2:$C$478,3,0),"AAA") -> 0 | H12: =IF(E12="","",0.21) -> 0.21 | I12: =IF('Global Precios'!H13="","",'Global Precios'!H13) -> 71605.785 | J12: =IF('Global Precios'!K13="","",'Global Precios'!K13) | K12: =IF('Global Precios'!Z13="Desactivado",0,IF('Global Precios'!L13="","",'Global Precios'!L13)) -> 87000 | R12: =IF('Global Precios'!F13="","",'Global Precios'!F13) -> Clinica | T12: =IF('Global Precios'!E13="","",'Global Precios'!E13) -> Arlekyn | V12: =IF(K12="","",0) -> 0 | AB12: =IF(K12="","",1) -> 1 | AC12: =IF(K12="","",1) -> 1 | AD12: =IF(K12="","",1) -> 1 | AE12: =AD12 -> 1
... A657: =IF(E657="","", IF('Global Precios'!B658="",0,'Global Precios'!B658)) -> 0 | B657: =IF('Global Precios'!B658="","",'Global Precios'!B658) | C657: =IF('Global Precios'!A658="","",'Global Precios'!A658) -> 689 | E657: =IF('Global Precios'!D658="","",'Global Precios'!D658) -> PONCHO TALLE 11 | G657: =IFERROR(VLOOKUP(C657,'BuscarV Stock'!$A$2:$C$478,3,0),"AAA") -> AAA | H657: =IF(E657="","",0.21) -> 0.21 | I657: =IF('Global Precios'!H658="","",'Global Precios'!H658) -> 3806.6116 | J657: =IF('Global Precios'!K658="","",'Global Precios'!K658) -> 0.8 | K657: =IF('Global Precios'!Z658="Desactivado",0,IF('Global Precios'!L658="","",'Global Precios'!L658)) -> 8300 | R657: =IF('Global Precios'!F658="","",'Global Precios'!F658) -> Pet-shop | T657: =IF('Global Precios'!E658="","",'Global Precios'!E658) | V657: =IF(K657="","",0) -> 0 | AB657: =IF(K657="","",1) -> 1 | AC657: =IF(K657="","",1) -> 1 | AD657: =IF(K657="","",1) -> 1 | AE657: =AD657 -> 1
A658: =IF(E658="","", IF('Global Precios'!B659="",0,'Global Precios'!B659)) -> 0 | B658: =IF('Global Precios'!B659="","",'Global Precios'!B659) | C658: =IF('Global Precios'!A659="","",'Global Precios'!A659) -> 692 | E658: =IF('Global Precios'!D659="","",'Global Precios'!D659) -> FLEE pulguicida y acaricida Aerosol | G658: =IFERROR(VLOOKUP(C658,'BuscarV Stock'!$A$2:$C$478,3,0),"AAA") -> AAA | H658: =IF(E658="","",0.21) -> 0.21 | I658: =IF('Global Precios'!H659="","",'Global Precios'!H659) -> 7851.2397 | J658: =IF('Global Precios'!K659="","",'Global Precios'!K659) | K658: =IF('Global Precios'!Z659="Desactivado",0,IF('Global Precios'!L659="","",'Global Precios'!L659)) -> 9500 | R658: =IF(#REF!="","",#REF!) -> #REF! | T658: =IF(#REF!="","",#REF!) -> #REF! | V658: =IF(K658="","",0) -> 0 | AB658: =IF(K658="","",1) -> 1 | AC658: =IF(K658="","",1) -> 1 | AD658: =IF(K658="","",1) -> 1 | AE658: =AD658 -> 1
A659: =IF(E659="","", IF('Global Precios'!B660="",0,'Global Precios'!B660)) -> 0 | B659: =IF('Global Precios'!B660="","",'Global Precios'!B660) | C659: =IF('Global Precios'!A660="","",'Global Precios'!A660) -> 693 | E659: =IF('Global Precios'!D660="","",'Global Precios'!D660) -> RESVITAL OMEGA ANTIOXIDANTE X 120 ML | G659: =IFERROR(VLOOKUP(C659,'BuscarV Stock'!$A$2:$C$478,3,0),"AAA") -> AAA | H659: =IF(E659="","",0.21) -> 0.21 | I659: =IF('Global Precios'!H660="","",'Global Precios'!H660) -> 12396.694 | J659: =IF('Global Precios'!K660="","",'Global Precios'!K660) | K659: =IF('Global Precios'!Z660="Desactivado",0,IF('Global Precios'!L660="","",'Global Precios'!L660)) -> 15000 | R659: =IF('Global Precios'!F659="","",'Global Precios'!F659) -> Medicamentos | T659: =IF('Global Precios'!E659="","",'Global Precios'!E659) -> Ruminal | V659: =IF(K659="","",0) -> 0 | AB659: =IF(K659="","",1) -> 1 | AC659: =IF(K659="","",1) -> 1 | AD659: =IF(K659="","",1) -> 1 | AE659: =AD659 -> 1
A660: =IF(E660="","", IF('Global Precios'!B661="",0,'Global Precios'!B661)) -> 0 | B660: =IF('Global Precios'!B661="","",'Global Precios'!B661) | C660: =IF('Global Precios'!A661="","",'Global Precios'!A661) -> 694 | E660: =IF('Global Precios'!D661="","",'Global Precios'!D661) -> PREGALBECH ORAL X 30 ML | G660: =IFERROR(VLOOKUP(C660,'BuscarV Stock'!$A$2:$C$478,3,0),"AAA") -> AAA | H660: =IF(E660="","",0.21) -> 0.21 | I660: =IF('Global Precios'!H661="","",'Global Precios'!H661) -> 14049.587 | J660: =IF('Global Precios'!K661="","",'Global Precios'!K661) | K660: =IF('Global Precios'!Z661="Desactivado",0,IF('Global Precios'!L661="","",'Global Precios'!L661)) -> 0 | R660: =IF('Global Precios'!F660="","",'Global Precios'!F660) -> Medicamentos | T660: =IF('Global Precios'!E660="","",'Global Precios'!E660) -> Bechlab | V660: =IF(K660="","",0) -> 0 | AB660: =IF(K660="","",1) -> 1 | AC660: =IF(K660="","",1) -> 1 | AD660: =IF(K660="","",1) -> 1 | AE660: =AD660 -> 1
A661: =IF(E661="","", IF('Global Precios'!B662="",0,'Global Precios'!B662)) -> 0 | B661: =IF('Global Precios'!B662="","",'Global Precios'!B662) | C661: =IF('Global Precios'!A662="","",'Global Precios'!A662) -> 695 | E661: =IF('Global Precios'!D662="","",'Global Precios'!D662) -> FLURAVET-C 20 kg | G661: =IFERROR(VLOOKUP(C661,'BuscarV Stock'!$A$2:$C$478,3,0),"AAA") -> AAA | H661: =IF(E661="","",0.21) -> 0.21 | I661: =IF('Global Precios'!H662="","",'Global Precios'!H662) -> 5206.6116 | J661: =IF('Global Precios'!K662="","",'Global Precios'!K662) | K661: =IF('Global Precios'!Z662="Desactivado",0,IF('Global Precios'!L662="","",'Global Precios'!L662)) -> 6300 | R661: =IF('Global Precios'!F661="","",'Global Precios'!F661) -> Medicamentos | T661: =IF('Global Precios'!E661="","",'Global Precios'!E661) -> Bechlab | V661: =IF(K661="","",0) -> 0 | AB661: =IF(K661="","",1) -> 1 | AC661: =IF(K661="","",1) -> 1 | AD661: =IF(K661="","",1) -> 1 | AE661: =AD661 -> 1
A662: =IF(E662="","", IF('Global Precios'!B663="",0,'Global Precios'!B663)) -> 0 | B662: =IF('Global Precios'!B663="","",'Global Precios'!B663) | C662: =IF('Global Precios'!A663="","",'Global Precios'!A663) -> 696 | E662: =IF('Global Precios'!D663="","",'Global Precios'!D663) -> FLURAVET-C 5 A 10 KG | G662: =IFERROR(VLOOKUP(C662,'BuscarV Stock'!$A$2:$C$478,3,0),"AAA") -> AAA | H662: =IF(E662="","",0.21) -> 0.21 | I662: =IF('Global Precios'!H663="","",'Global Precios'!H663) -> 9669.4215 | J662: =IF('Global Precios'!K663="","",'Global Precios'!K663) | K662: =IF('Global Precios'!Z663="Desactivado",0,IF('Global Precios'!L663="","",'Global Precios'!L663)) -> 11700 | R662: =IF('Global Precios'!F662="","",'Global Precios'!F662) -> Medicamentos | T662: =IF('Global Precios'!E662="","",'Global Precios'!E662) -> Alfa vet | V662: =IF(K662="","",0) -> 0 | AB662: =IF(K662="","",1) -> 1 | AC662: =IF(K662="","",1) -> 1 | AD662: =IF(K662="","",1) -> 1 | AE662: =AD662 -> 1
A663: =IF(E663="","", IF('Global Precios'!B664="",0,'Global Precios'!B664)) -> 0 | B663: =IF('Global Precios'!B664="","",'Global Precios'!B664) | C663: =IF('Global Precios'!A664="","",'Global Precios'!A664) -> 697 | E663: =IF('Global Precios'!D664="","",'Global Precios'!D664) -> TRILOBECH 10 MG X 10 COMP. | G663: =IFERROR(VLOOKUP(C663,'BuscarV Stock'!$A$2:$C$478,3,0),"AAA") -> AAA | H663: =IF(E663="","",0.21) -> 0.21 | I663: =IF('Global Precios'!H664="","",'Global Precios'!H664) -> 17355.372 | J663: =IF('Global Precios'!K664="","",'Global Precios'!K664) | K663: =IF('Global Precios'!Z664="Desactivado",0,IF('Global Precios'!L664="","",'Global Precios'!L664)) -> 21000 | R663: =IF('Global Precios'!F663="","",'Global Precios'!F663) -> Medicamentos | T663: =IF('Global Precios'!E663="","",'Global Precios'!E663) -> Alfa c | V663: =IF(K663="","",0) -> 0 | AB663: =IF(K663="","",1) -> 1 | AC663: =IF(K663="","",1) -> 1 | AD663: =IF(K663="","",1) -> 1 | AE663: =AD663 -> 1
A664: =IF(E664="","", IF('Global Precios'!B665="",0,'Global Precios'!B665)) -> 0 | B664: =IF('Global Precios'!B665="","",'Global Precios'!B665) | C664: =IF('Global Precios'!A665="","",'Global Precios'!A665) -> 698 | E664: =IF('Global Precios'!D665="","",'Global Precios'!D665) -> FLURAVET-C 4,6 A 10 kg | G664: =IFERROR(VLOOKUP(C664,'BuscarV Stock'!$A$2:$C$478,3,0),"AAA") -> AAA | H664: =IF(E664="","",0.21) -> 0.21 | I664: =IF('Global Precios'!H665="","",'Global Precios'!H665) -> 9917.3554 | J664: =IF('Global Precios'!K665="","",'Global Precios'!K665) | K664: =IF('Global Precios'!Z665="Desactivado",0,IF('Global Precios'!L665="","",'Global Precios'!L665)) -> 12000 | R664: =IF('Global Precios'!F664="","",'Global Precios'!F664) -> Medicamentos | T664: =IF('Global Precios'!E664="","",'Global Precios'!E664) -> Bechlab | V664: =IF(K664="","",0) -> 0 | AB664: =IF(K664="","",1) -> 1 | AC664: =IF(K664="","",1) -> 1 | AD664: =IF(K664="","",1) -> 1 | AE664: =AD664 -> 1
A665: =IF(E665="","", IF('Global Precios'!B666="",0,'Global Precios'!B666)) -> 0 | B665: =IF('Global Precios'!B666="","",'Global Precios'!B666) | C665: =IF('Global Precios'!A666="","",'Global Precios'!A666) -> 699 | E665: =IF('Global Precios'!D666="","",'Global Precios'!D666) -> FLURAVET-C 10 A 20 KG | G665: =IFERROR(VLOOKUP(C665,'BuscarV Stock'!$A$2:$C$478,3,0),"AAA") -> AAA | H665: =IF(E665="","",0.21) -> 0.21 | I665: =IF('Global Precios'!H666="","",'Global Precios'!H666) -> 12396.694 | J665: =IF('Global Precios'!K666="","",'Global Precios'!K666) | K665: =IF('Global Precios'!Z666="Desactivado",0,IF('Global Precios'!L666="","",'Global Precios'!L666)) -> 15000 | R665: =IF('Global Precios'!F665="","",'Global Precios'!F665) -> Medicamentos | T665: =IF('Global Precios'!E665="","",'Global Precios'!E665) -> Alfavet | V665: =IF(K665="","",0) -> 0 | AB665: =IF(K665="","",1) -> 1 | AC665: =IF(K665="","",1) -> 1 | AD665: =IF(K665="","",1) -> 1 | AE665: =AD665 -> 1
A666: =IF(E666="","", IF('Global Precios'!B667="",0,'Global Precios'!B667)) -> 0 | B666: =IF('Global Precios'!B667="","",'Global Precios'!B667) | C666: =IF('Global Precios'!A667="","",'Global Precios'!A667) -> 700 | E666: =IF('Global Precios'!D667="","",'Global Precios'!D667) -> FLURAVET-C 40 A 80 kg X 4 COMP. | G666: =IFERROR(VLOOKUP(C666,'BuscarV Stock'!$A$2:$C$478,3,0),"AAA") -> AAA | H666: =IF(E666="","",0.21) -> 0.21 | I666: =IF('Global Precios'!H667="","",'Global Precios'!H667) -> 5785.124 | J666: =IF('Global Precios'!K667="","",'Global Precios'!K667) | K666: =IF('Global Precios'!Z667="Desactivado",0,IF('Global Precios'!L667="","",'Global Precios'!L667)) -> 7000 | R666: =IF('Global Precios'!F666="","",'Global Precios'!F666) -> Medicamentos | T666: =IF('Global Precios'!E666="","",'Global Precios'!E666) -> Alfavet | V666: =IF(K666="","",0) -> 0 | AB666: =IF(K666="","",1) -> 1 | AC666: =IF(K666="","",1) -> 1 | AD666: =IF(K666="","",1) -> 1 | AE666: =AD666 -> 1
A667: =IF(E667="","", IF('Global Precios'!B668="",0,'Global Precios'!B668)) -> 0 | B667: =IF('Global Precios'!B668="","",'Global Precios'!B668) | C667: =IF('Global Precios'!A668="","",'Global Precios'!A668) -> 701 | E667: =IF('Global Precios'!D668="","",'Global Precios'!D668) -> PREGALBECH ORAL X 30 ML | G667: =IFERROR(VLOOKUP(C667,'BuscarV Stock'!$A$2:$C$478,3,0),"AAA") -> AAA | H667: =IF(E667="","",0.21) -> 0.21 | I667: =IF('Global Precios'!H668="","",'Global Precios'!H668) -> 14297.521 | J667: =IF('Global Precios'!K668="","",'Global Precios'!K668) | K667: =IF('Global Precios'!Z668="Desactivado",0,IF('Global Precios'!L668="","",'Global Precios'!L668)) -> 17300 | R667: =IF('Global Precios'!F667="","",'Global Precios'!F667) -> Medicamentos | T667: =IF('Global Precios'!E667="","",'Global Precios'!E667) -> Alfavet | V667: =IF(K667="","",0) -> 0 | AB667: =IF(K667="","",1) -> 1 | AC667: =IF(K667="","",1) -> 1 | AD667: =IF(K667="","",1) -> 1 | AE667: =AD667 -> 1
A668: =IF(E668="","", IF('Global Precios'!B669="",0,'Global Precios'!B669)) -> 0 | B668: =IF('Global Precios'!B669="","",'Global Precios'!B669) | C668: =IF('Global Precios'!A669="","",'Global Precios'!A669) -> 702 | E668: =IF('Global Precios'!D669="","",'Global Precios'!D669) -> GABALBECH ORAL X 30 ML | G668: =IFERROR(VLOOKUP(C668,'BuscarV Stock'!$A$2:$C$478,3,0),"AAA") -> AAA | H668: =IF(E668="","",0.21) -> 0.21 | I668: =IF('Global Precios'!H669="","",'Global Precios'!H669) -> 14297.521 | J668: =IF('Global Precios'!K669="","",'Global Precios'!K669) | K668: =IF('Global Precios'!Z669="Desactivado",0,IF('Global Precios'!L669="","",'Global Precios'!L669)) -> 17300 | R668: =IF('Global Precios'!F668="","",'Global Precios'!F668) -> Medicamentos | T668: =IF('Global Precios'!E668="","",'Global Precios'!E668) -> Bechlab | V668: =IF(K668="","",0) -> 0 | AB668: =IF(K668="","",1) -> 1 | AC668: =IF(K668="","",1) -> 1 | AD668: =IF(K668="","",1) -> 1 | AE668: =AD668 -> 1
A669: =IF(E669="","", IF('Global Precios'!B670="",0,'Global Precios'!B670)) -> 0 | B669: =IF('Global Precios'!B670="","",'Global Precios'!B670) | C669: =IF('Global Precios'!A670="","",'Global Precios'!A670) -> 703 | E669: =IF('Global Precios'!D670="","",'Global Precios'!D670) -> RENAL ADVANCED POLVO X 100 GRS | G669: =IFERROR(VLOOKUP(C669,'BuscarV Stock'!$A$2:$C$478,3,0),"AAA") -> AAA | H669: =IF(E669="","",0.21) -> 0.21 | I669: =IF('Global Precios'!H670="","",'Global Precios'!H670) -> 9423.9669 | J669: =IF('Global Precios'!K670="","",'Global Precios'!K670) | K669: =IF('Global Precios'!Z670="Desactivado",0,IF('Global Precios'!L670="","",'Global Precios'!L670)) -> 11400 | R669: =IF('Global Precios'!F669="","",'Global Precios'!F669) -> Medicamentos | T669: =IF('Global Precios'!E669="","",'Global Precios'!E669) -> Bechlab | V669: =IF(K669="","",0) -> 0 | AB669: =IF(K669="","",1) -> 1 | AC669: =IF(K669="","",1) -> 1 | AD669: =IF(K669="","",1) -> 1 | AE669: =AD669 -> 1
A670: =IF(E670="","", IF('Global Precios'!B671="",0,'Global Precios'!B671)) -> 0 | B670: =IF('Global Precios'!B671="","",'Global Precios'!B671) | C670: =IF('Global Precios'!A671="","",'Global Precios'!A671) -> 704 | E670: =IF('Global Precios'!D671="","",'Global Precios'!D671) -> NUTRIPET PALATABLE X 80 GRS | G670: =IFERROR(VLOOKUP(C670,'BuscarV Stock'!$A$2:$C$478,3,0),"AAA") -> AAA | H670: =IF(E670="","",0.21) -> 0.21 | I670: =IF('Global Precios'!H671="","",'Global Precios'!H671) -> 6446.281 | J670: =IF('Global Precios'!K671="","",'Global Precios'!K671) | K670: =IF('Global Precios'!Z671="Desactivado",0,IF('Global Precios'!L671="","",'Global Precios'!L671)) -> 7800 | R670: =IF('Global Precios'!F670="","",'Global Precios'!F670) -> Medicamentos | T670: =IF('Global Precios'!E670="","",'Global Precios'!E670) -> Bechlab | V670: =IF(K670="","",0) -> 0 | AB670: =IF(K670="","",1) -> 1 | AC670: =IF(K670="","",1) -> 1 | AD670: =IF(K670="","",1) -> 1 | AE670: =AD670 -> 1
... A677: =IF(E677="","", IF('Global Precios'!B678="",0,'Global Precios'!B678)) -> 0 | B677: =IF('Global Precios'!B678="","",'Global Precios'!B678) | C677: =IF('Global Precios'!A678="","",'Global Precios'!A678) -> 711 | E677: =IF('Global Precios'!D678="","",'Global Precios'!D678) -> JASPE GATO URINARY PREMIUM X 1 KG | G677: =IFERROR(VLOOKUP(C677,'BuscarV Stock'!$A$2:$C$478,3,0),"AAA") -> AAA | H677: =IF(E677="","",0.21) -> 0.21 | I677: =IF('Global Precios'!H678="","",'Global Precios'!H678) -> 3305.7851 | J677: =IF('Global Precios'!K678="","",'Global Precios'!K678) | K677: =IF('Global Precios'!Z678="Desactivado",0,IF('Global Precios'!L678="","",'Global Precios'!L678)) -> 4000 | R677: =IF('Global Precios'!F677="","",'Global Precios'!F677) -> Alimentos | T677: =IF('Global Precios'!E677="","",'Global Precios'!E677) -> EXCELLENT | V677: =IF(K677="","",0) -> 0 | AB677: =IF(K677="","",1) -> 1 | AC677: =IF(K677="","",1) -> 1 | AD677: =IF(K677="","",1) -> 1 | AE677: =AD677 -> 1
A678: =IF(E678="","", IF('Global Precios'!B686="",0,'Global Precios'!B686)) | B678: =IF('Global Precios'!B686="","",'Global Precios'!B686) | C678: =IF('Global Precios'!A686="","",'Global Precios'!A686) | E678: =IF('Global Precios'!D686="","",'Global Precios'!D686) | H678: =IF(E678="","",0.21) | I678: =IF('Global Precios'!H686="","",'Global Precios'!H686) | J678: =IF('Global Precios'!K686="","",'Global Precios'!K686) | K678: =IF('Global Precios'!Z686="Desactivado",0,IF('Global Precios'!L686="","",'Global Precios'!L686)) | R678: =IF('Global Precios'!F686="","",'Global Precios'!F686) | T678: =IF('Global Precios'!E686="","",'Global Precios'!E686) | V678: =IF(K678="","",0) | AB678: =IF(K678="","",1) | AC678: =IF(K678="","",1) | AD678: =IF(K678="","",1) | AE678: =AD678
A679: =IF(E679="","", IF('Global Precios'!B687="",0,'Global Precios'!B687)) | B679: =IF('Global Precios'!B687="","",'Global Precios'!B687) | C679: =IF('Global Precios'!A687="","",'Global Precios'!A687) | E679: =IF('Global Precios'!D687="","",'Global Precios'!D687) | H679: =IF(E679="","",0.21) | I679: =IF('Global Precios'!H687="","",'Global Precios'!H687) | J679: =IF('Global Precios'!K687="","",'Global Precios'!K687) | K679: =IF('Global Precios'!Z687="Desactivado",0,IF('Global Precios'!L687="","",'Global Precios'!L687)) | R679: =IF('Global Precios'!F687="","",'Global Precios'!F687) | T679: =IF('Global Precios'!E687="","",'Global Precios'!E687) | V679: =IF(K679="","",0) | AB679: =IF(K679="","",1) | AC679: =IF(K679="","",1) | AD679: =IF(K679="","",1) | AE679: =AD679
A680: =IF(E680="","", IF('Global Precios'!B688="",0,'Global Precios'!B688)) | B680: =IF('Global Precios'!B688="","",'Global Precios'!B688) | C680: =IF('Global Precios'!A688="","",'Global Precios'!A688) | E680: =IF('Global Precios'!D688="","",'Global Precios'!D688) | H680: =IF(E680="","",0.21) | I680: =IF('Global Precios'!H688="","",'Global Precios'!H688) | J680: =IF('Global Precios'!K688="","",'Global Precios'!K688) | K680: =IF('Global Precios'!Z688="Desactivado",0,IF('Global Precios'!L688="","",'Global Precios'!L688)) | R680: =IF('Global Precios'!F688="","",'Global Precios'!F688) | T680: =IF('Global Precios'!E688="","",'Global Precios'!E688) | V680: =IF(K680="","",0) | AB680: =IF(K680="","",1) | AC680: =IF(K680="","",1) | AD680: =IF(K680="","",1) | AE680: =AD680
A681: =IF(E681="","", IF('Global Precios'!B689="",0,'Global Precios'!B689)) | B681: =IF('Global Precios'!B689="","",'Global Precios'!B689) | C681: =IF('Global Precios'!A689="","",'Global Precios'!A689) | E681: =IF('Global Precios'!D689="","",'Global Precios'!D689) | H681: =IF(E681="","",0.21) | I681: =IF('Global Precios'!H689="","",'Global Precios'!H689) | J681: =IF('Global Precios'!K689="","",'Global Precios'!K689) | K681: =IF('Global Precios'!Z689="Desactivado",0,IF('Global Precios'!L689="","",'Global Precios'!L689)) | R681: =IF('Global Precios'!F689="","",'Global Precios'!F689) | T681: =IF('Global Precios'!E689="","",'Global Precios'!E689) | V681: =IF(K681="","",0) | AB681: =IF(K681="","",1) | AC681: =IF(K681="","",1) | AD681: =IF(K681="","",1) | AE681: =AD681
A682: =IF(E682="","", IF('Global Precios'!B690="",0,'Global Precios'!B690)) | B682: =IF('Global Precios'!B690="","",'Global Precios'!B690) | C682: =IF('Global Precios'!A690="","",'Global Precios'!A690) | E682: =IF('Global Precios'!D690="","",'Global Precios'!D690) | H682: =IF(E682="","",0.21) | I682: =IF('Global Precios'!H690="","",'Global Precios'!H690) | J682: =IF('Global Precios'!K690="","",'Global Precios'!K690) | K682: =IF('Global Precios'!Z690="Desactivado",0,IF('Global Precios'!L690="","",'Global Precios'!L690)) | R682: =IF('Global Precios'!F690="","",'Global Precios'!F690) | T682: =IF('Global Precios'!E690="","",'Global Precios'!E690) | V682: =IF(K682="","",0) | AB682: =IF(K682="","",1) | AC682: =IF(K682="","",1) | AD682: =IF(K682="","",1) | AE682: =AD682
A683: =IF(E683="","", IF('Global Precios'!B691="",0,'Global Precios'!B691)) | B683: =IF('Global Precios'!B691="","",'Global Precios'!B691) | C683: =IF('Global Precios'!A691="","",'Global Precios'!A691) | E683: =IF('Global Precios'!D691="","",'Global Precios'!D691) | H683: =IF(E683="","",0.21) | I683: =IF('Global Precios'!H691="","",'Global Precios'!H691) | J683: =IF('Global Precios'!K691="","",'Global Precios'!K691) | K683: =IF('Global Precios'!Z691="Desactivado",0,IF('Global Precios'!L691="","",'Global Precios'!L691)) | R683: =IF('Global Precios'!F691="","",'Global Precios'!F691) | T683: =IF('Global Precios'!E691="","",'Global Precios'!E691) | V683: =IF(K683="","",0) | AB683: =IF(K683="","",1) | AC683: =IF(K683="","",1) | AD683: =IF(K683="","",1) | AE683: =AD683
A684: =IF(E684="","", IF('Global Precios'!B692="",0,'Global Precios'!B692)) | B684: =IF('Global Precios'!B692="","",'Global Precios'!B692) | C684: =IF('Global Precios'!A692="","",'Global Precios'!A692) | E684: =IF('Global Precios'!D692="","",'Global Precios'!D692) | H684: =IF(E684="","",0.21) | I684: =IF('Global Precios'!H692="","",'Global Precios'!H692) | J684: =IF('Global Precios'!K692="","",'Global Precios'!K692) | K684: =IF('Global Precios'!Z692="Desactivado",0,IF('Global Precios'!L692="","",'Global Precios'!L692)) | R684: =IF('Global Precios'!F692="","",'Global Precios'!F692) | T684: =IF('Global Precios'!E692="","",'Global Precios'!E692) | V684: =IF(K684="","",0) | AB684: =IF(K684="","",1) | AC684: =IF(K684="","",1) | AD684: =IF(K684="","",1) | AE684: =AD684
A685: =IF(E685="","", IF('Global Precios'!B693="",0,'Global Precios'!B693)) | B685: =IF('Global Precios'!B693="","",'Global Precios'!B693) | C685: =IF('Global Precios'!A693="","",'Global Precios'!A693) | E685: =IF('Global Precios'!D693="","",'Global Precios'!D693) | H685: =IF(E685="","",0.21) | I685: =IF('Global Precios'!H693="","",'Global Precios'!H693) | J685: =IF('Global Precios'!K693="","",'Global Precios'!K693) | K685: =IF('Global Precios'!Z693="Desactivado",0,IF('Global Precios'!L693="","",'Global Precios'!L693)) | R685: =IF('Global Precios'!F693="","",'Global Precios'!F693) | T685: =IF('Global Precios'!E693="","",'Global Precios'!E693) | V685: =IF(K685="","",0) | AB685: =IF(K685="","",1) | AC685: =IF(K685="","",1) | AD685: =IF(K685="","",1) | AE685: =AD685
A686: =IF(E686="","", IF('Global Precios'!B694="",0,'Global Precios'!B694)) | B686: =IF('Global Precios'!B694="","",'Global Precios'!B694) | C686: =IF('Global Precios'!A694="","",'Global Precios'!A694) | E686: =IF('Global Precios'!D694="","",'Global Precios'!D694) | H686: =IF(E686="","",0.21) | I686: =IF('Global Precios'!H694="","",'Global Precios'!H694) | J686: =IF('Global Precios'!K694="","",'Global Precios'!K694) | K686: =IF('Global Precios'!Z694="Desactivado",0,IF('Global Precios'!L694="","",'Global Precios'!L694)) | R686: =IF('Global Precios'!F694="","",'Global Precios'!F694) | T686: =IF('Global Precios'!E694="","",'Global Precios'!E694) | V686: =IF(K686="","",0) | AB686: =IF(K686="","",1) | AC686: =IF(K686="","",1) | AD686: =IF(K686="","",1) | AE686: =AD686
A687: =IF(E687="","", IF('Global Precios'!B695="",0,'Global Precios'!B695)) | B687: =IF('Global Precios'!B695="","",'Global Precios'!B695) | C687: =IF('Global Precios'!A695="","",'Global Precios'!A695) | E687: =IF('Global Precios'!D695="","",'Global Precios'!D695) | H687: =IF(E687="","",0.21) | I687: =IF('Global Precios'!H695="","",'Global Precios'!H695) | J687: =IF('Global Precios'!K695="","",'Global Precios'!K695) | K687: =IF('Global Precios'!Z695="Desactivado",0,IF('Global Precios'!L695="","",'Global Precios'!L695)) | R687: =IF('Global Precios'!F695="","",'Global Precios'!F695) | T687: =IF('Global Precios'!E695="","",'Global Precios'!E695) | V687: =IF(K687="","",0) | AB687: =IF(K687="","",1) | AC687: =IF(K687="","",1) | AD687: =IF(K687="","",1) | AE687: =AD687
A688: =IF(E688="","", IF('Global Precios'!B696="",0,'Global Precios'!B696)) | B688: =IF('Global Precios'!B696="","",'Global Precios'!B696) | C688: =IF('Global Precios'!A696="","",'Global Precios'!A696) | E688: =IF('Global Precios'!D696="","",'Global Precios'!D696) | H688: =IF(E688="","",0.21) | I688: =IF('Global Precios'!H696="","",'Global Precios'!H696) | J688: =IF('Global Precios'!K696="","",'Global Precios'!K696) | K688: =IF('Global Precios'!Z696="Desactivado",0,IF('Global Precios'!L696="","",'Global Precios'!L696)) | R688: =IF('Global Precios'!F696="","",'Global Precios'!F696) | T688: =IF('Global Precios'!E696="","",'Global Precios'!E696) | V688: =IF(K688="","",0) | AB688: =IF(K688="","",1) | AC688: =IF(K688="","",1) | AD688: =IF(K688="","",1) | AE688: =AD688
A689: =IF(E689="","", IF('Global Precios'!B697="",0,'Global Precios'!B697)) | B689: =IF('Global Precios'!B697="","",'Global Precios'!B697) | C689: =IF('Global Precios'!A697="","",'Global Precios'!A697) | E689: =IF('Global Precios'!D697="","",'Global Precios'!D697) | H689: =IF(E689="","",0.21) | I689: =IF('Global Precios'!H697="","",'Global Precios'!H697) | J689: =IF('Global Precios'!K697="","",'Global Precios'!K697) | K689: =IF('Global Precios'!Z697="Desactivado",0,IF('Global Precios'!L697="","",'Global Precios'!L697)) | R689: =IF('Global Precios'!F697="","",'Global Precios'!F697) | T689: =IF('Global Precios'!E697="","",'Global Precios'!E697) | V689: =IF(K689="","",0) | AB689: =IF(K689="","",1) | AC689: =IF(K689="","",1) | AD689: =IF(K689="","",1) | AE689: =AD689
... A712: =IF(E712="","", IF('Global Precios'!B720="",0,'Global Precios'!B720)) | B712: =IF('Global Precios'!B720="","",'Global Precios'!B720) | C712: =IF('Global Precios'!A720="","",'Global Precios'!A720) | E712: =IF('Global Precios'!D720="","",'Global Precios'!D720) | H712: =IF(E712="","",0.21) | I712: =IF('Global Precios'!H720="","",'Global Precios'!H720) | J712: =IF('Global Precios'!K720="","",'Global Precios'!K720) | K712: =IF('Global Precios'!Z720="Desactivado",0,IF('Global Precios'!L720="","",'Global Precios'!L720)) | R712: =IF('Global Precios'!F720="","",'Global Precios'!F720) | T712: =IF('Global Precios'!E720="","",'Global Precios'!E720) | V712: =IF(K712="","",0) | AB712: =IF(K712="","",1) | AC712: =IF(K712="","",1) | AD712: =IF(K712="","",1) | AE712: =AD712
A713: =IF(E713="","", IF('Global Precios'!B717="",0,'Global Precios'!B717)) | B713: =IF('Global Precios'!B717="","",'Global Precios'!B717) | C713: =IF('Global Precios'!A717="","",'Global Precios'!A717) | E713: =IF('Global Precios'!D717="","",'Global Precios'!D717) | H713: =IF(E713="","",0.21) | I713: =IF('Global Precios'!H717="","",'Global Precios'!H717) | J713: =IF('Global Precios'!K717="","",'Global Precios'!K717) | K713: =IF('Global Precios'!Z717="Desactivado",0,IF('Global Precios'!L717="","",'Global Precios'!L717)) | R713: =IF('Global Precios'!F717="","",'Global Precios'!F717) | T713: =IF('Global Precios'!E717="","",'Global Precios'!E717) | V713: =IF(K713="","",0) | AB713: =IF(K713="","",1) | AC713: =IF(K713="","",1) | AD713: =IF(K713="","",1) | AE713: =AD713
A714: =IF(E714="","", IF('Global Precios'!B718="",0,'Global Precios'!B718)) | B714: =IF('Global Precios'!B718="","",'Global Precios'!B718) | C714: =IF('Global Precios'!A718="","",'Global Precios'!A718) | E714: =IF('Global Precios'!D718="","",'Global Precios'!D718) | H714: =IF(E714="","",0.21) | I714: =IF('Global Precios'!H718="","",'Global Precios'!H718) | J714: =IF('Global Precios'!K718="","",'Global Precios'!K718) | K714: =IF('Global Precios'!Z718="Desactivado",0,IF('Global Precios'!L718="","",'Global Precios'!L718)) | R714: =IF('Global Precios'!F718="","",'Global Precios'!F718) | T714: =IF('Global Precios'!E718="","",'Global Precios'!E718) | V714: =IF(K714="","",0) | AB714: =IF(K714="","",1) | AC714: =IF(K714="","",1) | AD714: =IF(K714="","",1) | AE714: =AD714
A715: =IF(E715="","", IF('Global Precios'!B719="",0,'Global Precios'!B719)) | B715: =IF('Global Precios'!B719="","",'Global Precios'!B719) | C715: =IF('Global Precios'!A719="","",'Global Precios'!A719) | E715: =IF('Global Precios'!D719="","",'Global Precios'!D719) | H715: =IF(E715="","",0.21) | I715: =IF('Global Precios'!H719="","",'Global Precios'!H719) | J715: =IF('Global Precios'!K719="","",'Global Precios'!K719) | K715: =IF('Global Precios'!Z719="Desactivado",0,IF('Global Precios'!L719="","",'Global Precios'!L719)) | R715: =IF('Global Precios'!F719="","",'Global Precios'!F719) | T715: =IF('Global Precios'!E719="","",'Global Precios'!E719) | V715: =IF(K715="","",0) | AB715: =IF(K715="","",1) | AC715: =IF(K715="","",1) | AD715: =IF(K715="","",1) | AE715: =AD715
A716: =IF(E716="","", IF('Global Precios'!B720="",0,'Global Precios'!B720)) | B716: =IF('Global Precios'!B720="","",'Global Precios'!B720) | C716: =IF('Global Precios'!A720="","",'Global Precios'!A720) | E716: =IF('Global Precios'!D720="","",'Global Precios'!D720) | H716: =IF(E716="","",0.21) | I716: =IF('Global Precios'!H720="","",'Global Precios'!H720) | J716: =IF('Global Precios'!K720="","",'Global Precios'!K720) | K716: =IF('Global Precios'!Z720="Desactivado",0,IF('Global Precios'!L720="","",'Global Precios'!L720)) | R716: =IF('Global Precios'!F720="","",'Global Precios'!F720) | T716: =IF('Global Precios'!E720="","",'Global Precios'!E720) | V716: =IF(K716="","",0) | AB716: =IF(K716="","",1) | AC716: =IF(K716="","",1) | AD716: =IF(K716="","",1) | AE716: =AD716
A717: =IF(E717="","", IF('Global Precios'!B721="",0,'Global Precios'!B721)) | B717: =IF('Global Precios'!B721="","",'Global Precios'!B721) | C717: =IF('Global Precios'!A721="","",'Global Precios'!A721) | E717: =IF('Global Precios'!D721="","",'Global Precios'!D721) | H717: =IF(E717="","",0.21) | I717: =IF('Global Precios'!H721="","",'Global Precios'!H721) | J717: =IF('Global Precios'!K721="","",'Global Precios'!K721) | K717: =IF('Global Precios'!Z721="Desactivado",0,IF('Global Precios'!L721="","",'Global Precios'!L721)) | R717: =IF('Global Precios'!F721="","",'Global Precios'!F721) | T717: =IF('Global Precios'!E721="","",'Global Precios'!E721) | V717: =IF(K717="","",0) | AB717: =IF(K717="","",1) | AC717: =IF(K717="","",1) | AD717: =IF(K717="","",1) | AE717: =AD717
A718: =IF(E718="","", IF('Global Precios'!B722="",0,'Global Precios'!B722)) | B718: =IF('Global Precios'!B722="","",'Global Precios'!B722) | C718: =IF('Global Precios'!A722="","",'Global Precios'!A722) | E718: =IF('Global Precios'!D722="","",'Global Precios'!D722) | H718: =IF(E718="","",0.21) | I718: =IF('Global Precios'!H722="","",'Global Precios'!H722) | J718: =IF('Global Precios'!K722="","",'Global Precios'!K722) | K718: =IF('Global Precios'!Z722="Desactivado",0,IF('Global Precios'!L722="","",'Global Precios'!L722)) | R718: =IF('Global Precios'!F722="","",'Global Precios'!F722) | T718: =IF('Global Precios'!E722="","",'Global Precios'!E722) | V718: =IF(K718="","",0) | AB718: =IF(K718="","",1) | AC718: =IF(K718="","",1) | AD718: =IF(K718="","",1) | AE718: =AD718
A719: =IF(E719="","", IF('Global Precios'!B723="",0,'Global Precios'!B723)) | B719: =IF('Global Precios'!B723="","",'Global Precios'!B723) | C719: =IF('Global Precios'!A723="","",'Global Precios'!A723) | E719: =IF('Global Precios'!D723="","",'Global Precios'!D723) | H719: =IF(E719="","",0.21) | I719: =IF('Global Precios'!H723="","",'Global Precios'!H723) | J719: =IF('Global Precios'!K723="","",'Global Precios'!K723) | K719: =IF('Global Precios'!Z723="Desactivado",0,IF('Global Precios'!L723="","",'Global Precios'!L723)) | R719: =IF('Global Precios'!F723="","",'Global Precios'!F723) | T719: =IF('Global Precios'!E723="","",'Global Precios'!E723) | V719: =IF(K719="","",0) | AB719: =IF(K719="","",1) | AC719: =IF(K719="","",1) | AD719: =IF(K719="","",1) | AE719: =AD719
A720: =IF(E720="","", IF('Global Precios'!B724="",0,'Global Precios'!B724)) | B720: =IF('Global Precios'!B724="","",'Global Precios'!B724) | C720: =IF('Global Precios'!A724="","",'Global Precios'!A724) | E720: =IF('Global Precios'!D724="","",'Global Precios'!D724) | H720: =IF(E720="","",0.21) | I720: =IF('Global Precios'!H724="","",'Global Precios'!H724) | J720: =IF('Global Precios'!K724="","",'Global Precios'!K724) | K720: =IF('Global Precios'!Z724="Desactivado",0,IF('Global Precios'!L724="","",'Global Precios'!L724)) | R720: =IF('Global Precios'!F724="","",'Global Precios'!F724) | T720: =IF('Global Precios'!E724="","",'Global Precios'!E724) | V720: =IF(K720="","",0) | AB720: =IF(K720="","",1) | AC720: =IF(K720="","",1) | AD720: =IF(K720="","",1) | AE720: =AD720
A721: =IF(E721="","", IF('Global Precios'!B725="",0,'Global Precios'!B725)) | B721: =IF('Global Precios'!B725="","",'Global Precios'!B725) | C721: =IF('Global Precios'!A725="","",'Global Precios'!A725) | E721: =IF('Global Precios'!D725="","",'Global Precios'!D725) | H721: =IF(E721="","",0.21) | I721: =IF('Global Precios'!H725="","",'Global Precios'!H725) | J721: =IF('Global Precios'!K725="","",'Global Precios'!K725) | K721: =IF('Global Precios'!Z725="Desactivado",0,IF('Global Precios'!L725="","",'Global Precios'!L725)) | R721: =IF('Global Precios'!F725="","",'Global Precios'!F725) | T721: =IF('Global Precios'!E725="","",'Global Precios'!E725) | V721: =IF(K721="","",0) | AB721: =IF(K721="","",1) | AC721: =IF(K721="","",1) | AD721: =IF(K721="","",1) | AE721: =AD721
A722: =IF(E722="","", IF('Global Precios'!B726="",0,'Global Precios'!B726)) | B722: =IF('Global Precios'!B726="","",'Global Precios'!B726) | C722: =IF('Global Precios'!A726="","",'Global Precios'!A726) | E722: =IF('Global Precios'!D726="","",'Global Precios'!D726) | H722: =IF(E722="","",0.21) | I722: =IF('Global Precios'!H726="","",'Global Precios'!H726) | J722: =IF('Global Precios'!K726="","",'Global Precios'!K726) | K722: =IF('Global Precios'!Z726="Desactivado",0,IF('Global Precios'!L726="","",'Global Precios'!L726)) | R722: =IF('Global Precios'!F726="","",'Global Precios'!F726) | T722: =IF('Global Precios'!E726="","",'Global Precios'!E726) | V722: =IF(K722="","",0) | AB722: =IF(K722="","",1) | AC722: =IF(K722="","",1) | AD722: =IF(K722="","",1) | AE722: =AD722
A723: =IF(E723="","", IF('Global Precios'!B727="",0,'Global Precios'!B727)) | B723: =IF('Global Precios'!B727="","",'Global Precios'!B727) | C723: =IF('Global Precios'!A727="","",'Global Precios'!A727) | E723: =IF('Global Precios'!D727="","",'Global Precios'!D727) | H723: =IF(E723="","",0.21) | I723: =IF('Global Precios'!H727="","",'Global Precios'!H727) | J723: =IF('Global Precios'!K727="","",'Global Precios'!K727) | K723: =IF('Global Precios'!Z727="Desactivado",0,IF('Global Precios'!L727="","",'Global Precios'!L727)) | R723: =IF('Global Precios'!F727="","",'Global Precios'!F727) | T723: =IF('Global Precios'!E727="","",'Global Precios'!E727) | V723: =IF(K723="","",0) | AB723: =IF(K723="","",1) | AC723: =IF(K723="","",1) | AD723: =IF(K723="","",1) | AE723: =AD723
A724: =IF(E724="","", IF('Global Precios'!B728="",0,'Global Precios'!B728)) | B724: =IF('Global Precios'!B728="","",'Global Precios'!B728) | C724: =IF('Global Precios'!A728="","",'Global Precios'!A728) | E724: =IF('Global Precios'!D728="","",'Global Precios'!D728) | H724: =IF(E724="","",0.21) | I724: =IF('Global Precios'!H728="","",'Global Precios'!H728) | J724: =IF('Global Precios'!K728="","",'Global Precios'!K728) | K724: =IF('Global Precios'!Z728="Desactivado",0,IF('Global Precios'!L728="","",'Global Precios'!L728)) | R724: =IF('Global Precios'!F728="","",'Global Precios'!F728) | T724: =IF('Global Precios'!E728="","",'Global Precios'!E728) | V724: =IF(K724="","",0) | AB724: =IF(K724="","",1) | AC724: =IF(K724="","",1) | AD724: =IF(K724="","",1) | AE724: =AD724
A725: =IF(E725="","", IF('Global Precios'!B727="",0,'Global Precios'!B727)) | B725: =IF('Global Precios'!B727="","",'Global Precios'!B727) | C725: =IF('Global Precios'!A727="","",'Global Precios'!A727) | E725: =IF('Global Precios'!D727="","",'Global Precios'!D727) | G725: =IF(E725="","",0) | H725: =IF(E725="","",0.21) | I725: =IF('Global Precios'!I727="","",'Global Precios'!I727) | J725: =IF('Global Precios'!K727="","",'Global Precios'!K727) | K725: =IF('Global Precios'!Z729="Desactivado",0,IF('Global Precios'!L729="","",'Global Precios'!L729)) | R725: =IF('Global Precios'!F727="","",'Global Precios'!F727) | T725: =IF('Global Precios'!E727="","",'Global Precios'!E727) | V725: =IF(K725="","",0) | AB725: =IF(K725="","",1) | AC725: =IF(K725="","",1) | AD725: =IF(K725="","",1) | AE725: =AD725
A726: =IF(E726="","", IF('Global Precios'!B728="",0,'Global Precios'!B728)) | B726: =IF('Global Precios'!B728="","",'Global Precios'!B728) | C726: =IF('Global Precios'!A728="","",'Global Precios'!A728) | E726: =IF('Global Precios'!D728="","",'Global Precios'!D728) | G726: =IF(E726="","",0) | H726: =IF(E726="","",0.21) | I726: =IF('Global Precios'!I728="","",'Global Precios'!I728) | J726: =IF('Global Precios'!K728="","",'Global Precios'!K728) | K726: =IF('Global Precios'!Z730="Desactivado",0,IF('Global Precios'!L730="","",'Global Precios'!L730)) | R726: =IF('Global Precios'!F728="","",'Global Precios'!F728) | T726: =IF('Global Precios'!E728="","",'Global Precios'!E728) | V726: =IF(K726="","",0) | AB726: =IF(K726="","",1) | AC726: =IF(K726="","",1) | AD726: =IF(K726="","",1) | AE726: =AD726
A727: =IF(E727="","", IF('Global Precios'!B729="",0,'Global Precios'!B729)) | B727: =IF('Global Precios'!B729="","",'Global Precios'!B729) | C727: =IF('Global Precios'!A729="","",'Global Precios'!A729) | E727: =IF('Global Precios'!D729="","",'Global Precios'!D729) | G727: =IF(E727="","",0) | H727: =IF(E727="","",0.21) | I727: =IF('Global Precios'!I729="","",'Global Precios'!I729) | J727: =IF('Global Precios'!K729="","",'Global Precios'!K729) | K727: =IF('Global Precios'!Z731="Desactivado",0,IF('Global Precios'!L731="","",'Global Precios'!L731)) | R727: =IF('Global Precios'!F729="","",'Global Precios'!F729) | T727: =IF('Global Precios'!E729="","",'Global Precios'!E729) | V727: =IF(K727="","",0) | AB727: =IF(K727="","",1) | AC727: =IF(K727="","",1) | AD727: =IF(K727="","",1) | AE727: =AD727
A728: =IF(E728="","", IF('Global Precios'!B730="",0,'Global Precios'!B730)) | B728: =IF('Global Precios'!B730="","",'Global Precios'!B730) | C728: =IF('Global Precios'!A730="","",'Global Precios'!A730) | E728: =IF('Global Precios'!D730="","",'Global Precios'!D730) | G728: =IF(E728="","",0) | H728: =IF(E728="","",0.21) | I728: =IF('Global Precios'!I730="","",'Global Precios'!I730) | J728: =IF('Global Precios'!K730="","",'Global Precios'!K730) | K728: =IF('Global Precios'!Z732="Desactivado",0,IF('Global Precios'!L732="","",'Global Precios'!L732)) | R728: =IF('Global Precios'!F730="","",'Global Precios'!F730) | T728: =IF('Global Precios'!E730="","",'Global Precios'!E730) | V728: =IF(K728="","",0) | AB728: =IF(K728="","",1) | AC728: =IF(K728="","",1) | AD728: =IF(K728="","",1) | AE728: =AD728
A729: =IF(E729="","", IF('Global Precios'!B731="",0,'Global Precios'!B731)) | B729: =IF('Global Precios'!B731="","",'Global Precios'!B731) | C729: =IF('Global Precios'!A731="","",'Global Precios'!A731) | E729: =IF('Global Precios'!D731="","",'Global Precios'!D731) | G729: =IF(E729="","",0) | H729: =IF(E729="","",0.21) | I729: =IF('Global Precios'!I731="","",'Global Precios'!I731) | J729: =IF('Global Precios'!K731="","",'Global Precios'!K731) | K729: =IF('Global Precios'!Z733="Desactivado",0,IF('Global Precios'!L733="","",'Global Precios'!L733)) | R729: =IF('Global Precios'!F731="","",'Global Precios'!F731) | T729: =IF('Global Precios'!E731="","",'Global Precios'!E731) | V729: =IF(K729="","",0) | AB729: =IF(K729="","",1) | AC729: =IF(K729="","",1) | AD729: =IF(K729="","",1) | AE729: =AD729
A730: =IF(E730="","", IF('Global Precios'!B732="",0,'Global Precios'!B732)) | B730: =IF('Global Precios'!B732="","",'Global Precios'!B732) | C730: =IF('Global Precios'!A732="","",'Global Precios'!A732) | E730: =IF('Global Precios'!D732="","",'Global Precios'!D732) | G730: =IF(E730="","",0) | H730: =IF(E730="","",0.21) | I730: =IF('Global Precios'!I732="","",'Global Precios'!I732) | J730: =IF('Global Precios'!K732="","",'Global Precios'!K732) | K730: =IF('Global Precios'!Z734="Desactivado",0,IF('Global Precios'!L734="","",'Global Precios'!L734)) | R730: =IF('Global Precios'!F732="","",'Global Precios'!F732) | T730: =IF('Global Precios'!E732="","",'Global Precios'!E732) | V730: =IF(K730="","",0) | AB730: =IF(K730="","",1) | AC730: =IF(K730="","",1) | AD730: =IF(K730="","",1) | AE730: =AD730
A731: =IF(E731="","", IF('Global Precios'!B733="",0,'Global Precios'!B733)) | B731: =IF('Global Precios'!B733="","",'Global Precios'!B733) | C731: =IF('Global Precios'!A733="","",'Global Precios'!A733) | E731: =IF('Global Precios'!D733="","",'Global Precios'!D733) | G731: =IF(E731="","",0) | H731: =IF(E731="","",0.21) | I731: =IF('Global Precios'!I733="","",'Global Precios'!I733) | J731: =IF('Global Precios'!K733="","",'Global Precios'!K733) | K731: =IF('Global Precios'!Z735="Desactivado",0,IF('Global Precios'!L735="","",'Global Precios'!L735)) | R731: =IF('Global Precios'!F733="","",'Global Precios'!F733) | T731: =IF('Global Precios'!E733="","",'Global Precios'!E733) | V731: =IF(K731="","",0) | AB731: =IF(K731="","",1) | AC731: =IF(K731="","",1) | AD731: =IF(K731="","",1) | AE731: =AD731
A732: =IF(E732="","", IF('Global Precios'!B734="",0,'Global Precios'!B734)) | B732: =IF('Global Precios'!B734="","",'Global Precios'!B734) | C732: =IF('Global Precios'!A734="","",'Global Precios'!A734) | E732: =IF('Global Precios'!D734="","",'Global Precios'!D734) | G732: =IF(E732="","",0) | H732: =IF(E732="","",0.21) | I732: =IF('Global Precios'!I734="","",'Global Precios'!I734) | J732: =IF('Global Precios'!K734="","",'Global Precios'!K734) | K732: =IF('Global Precios'!Z736="Desactivado",0,IF('Global Precios'!L736="","",'Global Precios'!L736)) | R732: =IF('Global Precios'!F734="","",'Global Precios'!F734) | T732: =IF('Global Precios'!E734="","",'Global Precios'!E734) | V732: =IF(K732="","",0) | AB732: =IF(K732="","",1) | AC732: =IF(K732="","",1) | AD732: =IF(K732="","",1) | AE732: =AD732
A733: =IF(E733="","", IF('Global Precios'!B735="",0,'Global Precios'!B735)) | B733: =IF('Global Precios'!B735="","",'Global Precios'!B735) | C733: =IF('Global Precios'!A735="","",'Global Precios'!A735) | E733: =IF('Global Precios'!D735="","",'Global Precios'!D735) | G733: =IF(E733="","",0) | H733: =IF(E733="","",0.21) | I733: =IF('Global Precios'!I735="","",'Global Precios'!I735) | J733: =IF('Global Precios'!K735="","",'Global Precios'!K735) | K733: =IF('Global Precios'!L735="","",'Global Precios'!L735) | R733: =IF('Global Precios'!F735="","",'Global Precios'!F735) | T733: =IF('Global Precios'!E735="","",'Global Precios'!E735) | V733: =IF(K733="","",0) | AB733: =IF(K733="","",1) | AC733: =IF(K733="","",1) | AD733: =IF(K733="","",1) | AE733: =AD733
A734: =IF(E734="","", IF('Global Precios'!B736="",0,'Global Precios'!B736)) | B734: =IF('Global Precios'!B736="","",'Global Precios'!B736) | C734: =IF('Global Precios'!A736="","",'Global Precios'!A736) | E734: =IF('Global Precios'!D736="","",'Global Precios'!D736) | G734: =IF(E734="","",0) | H734: =IF(E734="","",0.21) | I734: =IF('Global Precios'!I736="","",'Global Precios'!I736) | J734: =IF('Global Precios'!K736="","",'Global Precios'!K736) | K734: =IF('Global Precios'!L736="","",'Global Precios'!L736) | R734: =IF('Global Precios'!F736="","",'Global Precios'!F736) | T734: =IF('Global Precios'!E736="","",'Global Precios'!E736) | V734: =IF(K734="","",0) | AB734: =IF(K734="","",1) | AC734: =IF(K734="","",1) | AD734: =IF(K734="","",1) | AE734: =AD734
A735: =IF(E735="","", IF('Global Precios'!B737="",0,'Global Precios'!B737)) | B735: =IF('Global Precios'!B737="","",'Global Precios'!B737) | C735: =IF('Global Precios'!A737="","",'Global Precios'!A737) | E735: =IF('Global Precios'!D737="","",'Global Precios'!D737) | G735: =IF(E735="","",0) | H735: =IF(E735="","",0.21) | I735: =IF('Global Precios'!I737="","",'Global Precios'!I737) | J735: =IF('Global Precios'!K737="","",'Global Precios'!K737) | K735: =IF('Global Precios'!L737="","",'Global Precios'!L737) | R735: =IF('Global Precios'!F737="","",'Global Precios'!F737) | T735: =IF('Global Precios'!E737="","",'Global Precios'!E737) | V735: =IF(K735="","",0) | AB735: =IF(K735="","",1) | AC735: =IF(K735="","",1) | AD735: =IF(K735="","",1) | AE735: =AD735
A736: =IF(E736="","", IF('Global Precios'!B738="",0,'Global Precios'!B738)) | B736: =IF('Global Precios'!B738="","",'Global Precios'!B738) | C736: =IF('Global Precios'!A738="","",'Global Precios'!A738) | E736: =IF('Global Precios'!D738="","",'Global Precios'!D738) | G736: =IF(E736="","",0) | H736: =IF(E736="","",0.21) | I736: =IF('Global Precios'!I738="","",'Global Precios'!I738) | J736: =IF('Global Precios'!K738="","",'Global Precios'!K738) | K736: =IF('Global Precios'!L738="","",'Global Precios'!L738) | R736: =IF('Global Precios'!F738="","",'Global Precios'!F738) | T736: =IF('Global Precios'!E738="","",'Global Precios'!E738) | V736: =IF(K736="","",0) | AB736: =IF(K736="","",1) | AC736: =IF(K736="","",1) | AD736: =IF(K736="","",1) | AE736: =AD736
A737: =IF(E737="","", IF('Global Precios'!B739="",0,'Global Precios'!B739)) | B737: =IF('Global Precios'!B739="","",'Global Precios'!B739) | C737: =IF('Global Precios'!A739="","",'Global Precios'!A739) | E737: =IF('Global Precios'!D739="","",'Global Precios'!D739) | G737: =IF(E737="","",0) | H737: =IF(E737="","",0.21) | I737: =IF('Global Precios'!I739="","",'Global Precios'!I739) | J737: =IF('Global Precios'!K739="","",'Global Precios'!K739) | K737: =IF('Global Precios'!L739="","",'Global Precios'!L739) | R737: =IF('Global Precios'!F739="","",'Global Precios'!F739) | T737: =IF('Global Precios'!E739="","",'Global Precios'!E739) | V737: =IF(K737="","",0) | AB737: =IF(K737="","",1) | AC737: =IF(K737="","",1) | AD737: =IF(K737="","",1) | AE737: =AD737
A738: =IF(E738="","", IF('Global Precios'!B740="",0,'Global Precios'!B740)) | B738: =IF('Global Precios'!B740="","",'Global Precios'!B740) | C738: =IF('Global Precios'!A740="","",'Global Precios'!A740) | E738: =IF('Global Precios'!D740="","",'Global Precios'!D740) | G738: =IF(E738="","",0) | H738: =IF(E738="","",0.21) | I738: =IF('Global Precios'!I740="","",'Global Precios'!I740) | J738: =IF('Global Precios'!K740="","",'Global Precios'!K740) | K738: =IF('Global Precios'!L740="","",'Global Precios'!L740) | R738: =IF('Global Precios'!F740="","",'Global Precios'!F740) | T738: =IF('Global Precios'!E740="","",'Global Precios'!E740) | V738: =IF(K738="","",0) | AB738: =IF(K738="","",1) | AC738: =IF(K738="","",1) | AD738: =IF(K738="","",1) | AE738: =AD738
A739: =IF(E739="","", IF('Global Precios'!B741="",0,'Global Precios'!B741)) | B739: =IF('Global Precios'!B741="","",'Global Precios'!B741) | C739: =IF('Global Precios'!A741="","",'Global Precios'!A741) | E739: =IF('Global Precios'!D741="","",'Global Precios'!D741) | G739: =IF(E739="","",0) | H739: =IF(E739="","",0.21) | I739: =IF('Global Precios'!I741="","",'Global Precios'!I741) | J739: =IF('Global Precios'!K741="","",'Global Precios'!K741) | K739: =IF('Global Precios'!L741="","",'Global Precios'!L741) | R739: =IF('Global Precios'!F741="","",'Global Precios'!F741) | T739: =IF('Global Precios'!E741="","",'Global Precios'!E741) | V739: =IF(K739="","",0) | AB739: =IF(K739="","",1) | AC739: =IF(K739="","",1) | AD739: =IF(K739="","",1) | AE739: =AD739
A740: =IF(E740="","", IF('Global Precios'!B742="",0,'Global Precios'!B742)) | B740: =IF('Global Precios'!B742="","",'Global Precios'!B742) | C740: =IF('Global Precios'!A742="","",'Global Precios'!A742) | E740: =IF('Global Precios'!D742="","",'Global Precios'!D742) | G740: =IF(E740="","",0) | H740: =IF(E740="","",0.21) | I740: =IF('Global Precios'!I742="","",'Global Precios'!I742) | J740: =IF('Global Precios'!K742="","",'Global Precios'!K742) | K740: =IF('Global Precios'!L742="","",'Global Precios'!L742) | R740: =IF('Global Precios'!F742="","",'Global Precios'!F742) | T740: =IF('Global Precios'!E742="","",'Global Precios'!E742) | V740: =IF(K740="","",0) | AB740: =IF(K740="","",1) | AC740: =IF(K740="","",1) | AD740: =IF(K740="","",1) | AE740: =AD740
A741: =IF(E741="","", IF('Global Precios'!B743="",0,'Global Precios'!B743)) | B741: =IF('Global Precios'!B743="","",'Global Precios'!B743) | C741: =IF('Global Precios'!A743="","",'Global Precios'!A743) | E741: =IF('Global Precios'!D743="","",'Global Precios'!D743) | G741: =IF(E741="","",0) | H741: =IF(E741="","",0.21) | I741: =IF('Global Precios'!I743="","",'Global Precios'!I743) | J741: =IF('Global Precios'!K743="","",'Global Precios'!K743) | K741: =IF('Global Precios'!L743="","",'Global Precios'!L743) | R741: =IF('Global Precios'!F743="","",'Global Precios'!F743) | T741: =IF('Global Precios'!E743="","",'Global Precios'!E743) | V741: =IF(K741="","",0) | AB741: =IF(K741="","",1) | AC741: =IF(K741="","",1) | AD741: =IF(K741="","",1) | AE741: =AD741
A742: =IF(E742="","", IF('Global Precios'!B744="",0,'Global Precios'!B744)) | B742: =IF('Global Precios'!B744="","",'Global Precios'!B744) | C742: =IF('Global Precios'!A744="","",'Global Precios'!A744) | E742: =IF('Global Precios'!D744="","",'Global Precios'!D744) | G742: =IF(E742="","",0) | H742: =IF(E742="","",0.21) | I742: =IF('Global Precios'!I744="","",'Global Precios'!I744) | J742: =IF('Global Precios'!K744="","",'Global Precios'!K744) | K742: =IF('Global Precios'!L744="","",'Global Precios'!L744) | R742: =IF('Global Precios'!F744="","",'Global Precios'!F744) | T742: =IF('Global Precios'!E744="","",'Global Precios'!E744) | V742: =IF(K742="","",0) | AB742: =IF(K742="","",1) | AC742: =IF(K742="","",1) | AD742: =IF(K742="","",1) | AE742: =AD742
A743: =IF(E743="","", IF('Global Precios'!B745="",0,'Global Precios'!B745)) | B743: =IF('Global Precios'!B745="","",'Global Precios'!B745) | C743: =IF('Global Precios'!A745="","",'Global Precios'!A745) | E743: =IF('Global Precios'!D745="","",'Global Precios'!D745) | G743: =IF(E743="","",0) | H743: =IF(E743="","",0.21) | I743: =IF('Global Precios'!I745="","",'Global Precios'!I745) | J743: =IF('Global Precios'!K745="","",'Global Precios'!K745) | K743: =IF('Global Precios'!L745="","",'Global Precios'!L745) | R743: =IF('Global Precios'!F745="","",'Global Precios'!F745) | T743: =IF('Global Precios'!E745="","",'Global Precios'!E745) | V743: =IF(K743="","",0) | AB743: =IF(K743="","",1) | AC743: =IF(K743="","",1) | AD743: =IF(K743="","",1) | AE743: =AD743
A744: =IF(E744="","", IF('Global Precios'!B746="",0,'Global Precios'!B746)) | B744: =IF('Global Precios'!B746="","",'Global Precios'!B746) | C744: =IF('Global Precios'!A746="","",'Global Precios'!A746) | E744: =IF('Global Precios'!D746="","",'Global Precios'!D746) | G744: =IF(E744="","",0) | H744: =IF(E744="","",0.21) | I744: =IF('Global Precios'!I746="","",'Global Precios'!I746) | J744: =IF('Global Precios'!K746="","",'Global Precios'!K746) | K744: =IF('Global Precios'!L746="","",'Global Precios'!L746) | R744: =IF('Global Precios'!F746="","",'Global Precios'!F746) | T744: =IF('Global Precios'!E746="","",'Global Precios'!E746) | V744: =IF(K744="","",0) | AB744: =IF(K744="","",1) | AC744: =IF(K744="","",1) | AD744: =IF(K744="","",1) | AE744: =AD744
... A988: =IF(E988="","", IF('Global Precios'!B990="",0,'Global Precios'!B990)) | B988: =IF('Global Precios'!B990="","",'Global Precios'!B990) | C988: =IF('Global Precios'!A990="","",'Global Precios'!A990) | E988: =IF('Global Precios'!D990="","",'Global Precios'!D990) | G988: =IF(E988="","",0) | H988: =IF(E988="","",0.21) | I988: =IF('Global Precios'!I990="","",'Global Precios'!I990) | J988: =IF('Global Precios'!K990="","",'Global Precios'!K990) | K988: =IF('Global Precios'!L990="","",'Global Precios'!L990) | R988: =IF('Global Precios'!F990="","",'Global Precios'!F990) | T988: =IF('Global Precios'!E990="","",'Global Precios'!E990) | V988: =IF(K988="","",0) | AB988: =IF(K988="","",1) | AC988: =IF(K988="","",1) | AD988: =IF(K988="","",1) | AE988: =AD988

Sheet BUSCARV
A1: ARTÍCULO | B1: Costo c/iva
A2: BERMAT ORAL X 1 LTS | B2: 29077
A3: DERRIBANTE ACA X 4 LTS (AMITRAZ 12,5%) | B3: 126834
A4: DERRIBANTE IXO PO X 5 LTS (FLUAZ. 2,5%) | B4: 286188
A5: DERRIBANTE POUR ON X 1 LT | B5: 28433
A6: DERRIBANTE POUR ON X 5 LT | B6: 125314
A7: DERRIBANTE SM X 5 LTS | B7: 294028
A8: DERRIBANTE TAKLE X 1 LT | B8: 114799
A9: DERRIBANTE TAKLE X 5 LTS | B9: 538239
A10: IMIDAC X 100 ML (IMIDOCARB 12%) | B10: 47358
A11: INANDEX 1% X 500 ML | B11: 20048
A12: INANDEX 3.15 X 500 ML | B12: 36556
A13: OPTIMISOL X 500 ML | B13: 27573
... A3770: ZIFLOR CREMA CICATRIZANTE X 15 GR | B3770: 10128

Sheet BuscarV Stock
A1: ID | B1: Producto | C1: Stock
A2: 1 | B2: Castración Gata | C2: 0
A3: 2 | B3: Castración perra hasta 10 kg | C3: 0
A4: 3 | B4: Castración perra hasta 20 kg | C4: 0
A5: 4 | B5: Castración perra hasta 30 kg | C5: 0
A6: 5 | B6: Castración perra hasta 40 kg | C6: 0
A7: 6 | B7: Castración perra hasta 50 kg | C7: 0
A8: 7 | B8: Castración perra hasta 60 kg | C8: 0
A9: 8 | B9: Corte de colitas camadas hasta 3 cachorros | C9: 0
A10: 9 | B10: Corte de colitas camadas hasta 4 cachorros | C10: 0
A11: 10 | B11: Eutanasia hasta 10 kg | C11: 0
A12: 11 | B12: Eutanasia hasta 20 kg | C12: 0
A13: 12 | B13: Eutanasia hasta 30 kg | C13: 0
... A98: 97 | B98: APTO X 160 COMP | C98: 0
A99: 98 | C99: 0
A100: 99 | B100: FELINE FULLSPOT 02-05 KG | C100: 1
A101: 100 | B101: LAPIPETA DE 11 A 20 KG | C101: 1
A102: 101 | B102: LAPIPETA DE 2 A 10 KG | C102: 6
A103: 102 | B103: LAPIPETA DE 21 A 40 KG | C103: 2
A104: 103 | B104: LAPIPETA GATOS 0 A 4 KG | C104: 0
A105: 104 | B105: LAPIPETA GATOS 4 A 8 KG | C105: 3
A106: 105 | B106: LAPIPETA MÁS DE 40 KG | C106: 10
A107: 106 | B107: EPISOL X 9 COMP | C107: 4
A108: 107 | B108: FRONTLINE SPRAY X 100 ML | C108: 0
A109: 108 | B109: ANULADO | C109: 0
A110: 109 | B110: PIMODEN 10 MG X Blister x 10 COMP. | C110: 14
A111: 111 | B111: Cardinas medianas | C111: 1
... A418: 446 | B418: Nogastrol | C418: 0
A419: 447 | B419: NOGASTROL X 10 COMPRIMIDOS | C419: 0.6
A420: 448 | B420: MV RENAL CANINOS X 2 KG | C420: 0
A421: 449 | B421: RECOVERY LATA | C421: 0
A422: 450 | B422: DOXICICLINA SUSPENSIÓN X 20 ML | C422: 0
A423: 451 | B423: DENTASTIX RAZAS PEQUEÑAS X 3 | C423: 4
A424: 452 | B424: DENTASTIX RAZAS MEDIANAS X 3 | C424: 4
A425: 453 | B425: RODEO CARNE/POLLO | C425: 0
A426: 454 | B426: MV URINARY GATOS | C426: 1
A427: 455 | B427: BRAVECTO GATOS PIPETA 2,8 A 6,25 KG | C427: 0
A428: 456 | B428: CORTE DE UÑAS Y RECORTE DE PELO PERRO CHICO | C428: 0
A429: 457 | B429: CORTE DE UÑAS Y RECORTE DE PELO PERRO MEDIANO | C429: 0
A430: 458 | B430: CORTE DE UÑAS Y RECORTE DE PELO PERRO GRANDE | C430: 0
A431: 459 | B431: SPINOMAX DUO 4-9 KG X COMPRIMIDO | C431: 0
... A478: 506 | B478: VACUNA LEPTO NOVIBAC | C478: 0

Sheet Validación
A1: Categorías | B1: Tipo | C1: Subcategorias | D1: Marca
A2: Medicamentos | B2: Producto | C2: PERRO
A3: Alimentos | B3: Servicio | C3: GATO
A4: Peluquería | C4: VITAMINAS Y PROT. HEPATICOS,ETC
A5: Clinica | C5: CREMAS
A6: Cirugias | C6: LIQUIDOS Y SHAMPOOS
A7: Pet-shop | C7: ANTIIINFLAMATORIOS Y ANALGÉSICOS
A8: Insumos | C8: ANTIBIÓTICOS
C9: OIDOS
C10: PIPETAS
C11: ANTIPARASITARIOS INTERNOS
C12: OJOS
C13: PASTILLAS PULGAS,GARRAPATAS,ACAROS
C14: CARDIOLOGICOS
C15: CARDINAS
C16: BAÑO
C17: HIGIENE
C18: COLLARES
C19: CORREAS
C20: CORREAS Y COLLARES (KIT)
... C26: ANTICONVULSIVANTES

Sheet Categorías
A1: ID | B1: Categoria
A2: 1 | B2: Medicamentos
A3: 2 | B3: Alimentos
A4: 3 | B4: Peluquería
A5: 4 | B5: Clinica
A6: 5 | B6: Cirugias
A7: 6 | B7: Pet-shop
A8: 7 | B8: Insumos
A9: 8 | B9: Fisioterapia

Sheet Aplicación
E1: c/iva | F1: s/iva
B2: Campos que se pueden actualizar y campos que no | D2: red comercial | F2: *
B3: Ordenamiento de la ficha del producto, y tamaños | D3: Alfavet | E3: *
B4: Que la fecha de ultima actualización se ponga sola cuando modifico el producto | D4: Fernandito | E4: *
B5: Colocar una columna con frecuencia de actualización para que me tire para actualizar solo cuando sea | D5: Veronica insumos | E5: *
B6: Que ponga primero los productos que hay que actualizar | D6: kitvet | E6: *
B7: Un campo para foto del producto, va a ser muy util para lo que es pet-shop | D7: Purina | E7: * | F7: *
B8: Adaptar la app para que pueda poner los precios con Iva unicamente | D8: vasques | E8: *
B9: Que el margen aparezca como porcentaje
B10: El ID creciente y correlativo
B11: Los costos a ingresar que sean sin coma y tengan el signo pesos en la ficha
B12: Campos requeridos
B13: Que no se pueda eliminar ningun producto
B14: Logo de la app | G14: =30-7 -> 23
B15: campos editables | G15: =60-7 -> 53
B16: Que cuando la frecuencia de actualización sea 0 entonces se tome como
B17: Ver para que la alerta de actualización salte por frecuencia de mes y no por la cantidad de días

Sheet Ajuste
A1: Id | B1: % de ajuste
A2: 1 | B2: 0.02
